{
 "version": "2.0.0",
 "scrollSpeed": {
  "easy": 1.1,
  "hard": 1.6,
  "normal": 1.4
 },
 "events": [
  {
   "t": 0,
   "e": "FocusCamera",
   "v": {
	"char": 1
}
  },
  {
   "t": 2526.31578947368,
   "e": "FocusCamera",
   "v": {
	"ease": "CLASSIC",
	"char": 0
}
  },
  {
   "t": 5052.63157894737,
   "e": "FocusCamera",
   "v": {
	"ease": "CLASSIC",
	"char": 1
}
  },
  {
   "t": 7578.94736842105,
   "e": "FocusCamera",
   "v": {
	"ease": "CLASSIC",
	"char": 0
}
  },
  {
   "t": 9947.36842105263,
   "e": "SetCameraBop",
   "v": {
	"rate": 2,
	"intensity": 1
}
  },
  {
   "t": 10105.2631578947,
   "e": "FocusCamera",
   "v": {
	"ease": "CLASSIC",
	"char": 1
}
  },
  {
   "t": 17684.2105263158,
   "e": "FocusCamera",
   "v": {
	"ease": "CLASSIC",
	"char": 2
}
  },
  {
   "t": 20210.5263157895,
   "e": "FocusCamera",
   "v": {
	"ease": "CLASSIC",
	"char": 1
}
  },
  {
   "t": 25263.1578947368,
   "e": "FocusCamera",
   "v": {
	"ease": "CLASSIC",
	"char": 0
}
  },
  {
   "t": 30315.7894736842,
   "e": "FocusCamera",
   "v": {
	"ease": "CLASSIC",
	"char": 1
}
  },
  {
   "t": 35368.4210526316,
   "e": "FocusCamera",
   "v": {
	"ease": "CLASSIC",
	"char": 0
}
  },
  {
   "t": 37736.8421052632,
   "e": "SetCameraBop",
   "v": {
	"rate": 4,
	"intensity": 1
}
  },
  {
   "t": 40263.1578947368,
   "e": "SetCameraBop",
   "v": {
	"rate": 2,
	"intensity": 1
}
  },
  {
   "t": 40421.0526315789,
   "e": "FocusCamera",
   "v": {
	"ease": "CLASSIC",
	"char": 1
}
  },
  {
   "t": 45473.6842105263,
   "e": "FocusCamera",
   "v": {
	"ease": "CLASSIC",
	"char": 0
}
  },
  {
   "t": 50526.3157894737,
   "e": "FocusCamera",
   "v": {
	"ease": "CLASSIC",
	"char": 1
}
  },
  {
   "t": 55578.9473684211,
   "e": "FocusCamera",
   "v": {
	"ease": "CLASSIC",
	"char": 0
}
  },
  {
   "t": 57947.3684210526,
   "e": "SetCameraBop",
   "v": {
	"rate": 4,
	"intensity": 1
}
  },
  {
   "t": 60473.6842105263,
   "e": "SetCameraBop",
   "v": {
	"rate": 2,
	"intensity": 1,
	"offset": 1
}
  },
  {
   "t": 60631.5789473684,
   "e": "FocusCamera",
   "v": {
	"ease": "CLASSIC",
	"char": 1
}
  },
  {
   "t": 65684.2105263158,
   "e": "FocusCamera",
   "v": {
	"ease": "CLASSIC",
	"char": 0
}
  },
  {
   "t": 70578.9473684211,
   "e": "SetCameraBop",
   "v": {
	"rate": 2,
	"intensity": 1,
	"offset": 0
}
  },
  {
   "t": 70736.8421052632,
   "e": "FocusCamera",
   "v": {
	"ease": "CLASSIC",
	"char": 1
}
  },
  {
   "t": 72000,
   "e": "FocusCamera",
   "v": {
	"ease": "CLASSIC",
	"char": 0
}
  },
  {
   "t": 73263.1578947368,
   "e": "FocusCamera",
   "v": {
	"ease": "CLASSIC",
	"char": 1
}
  },
  {
   "t": 74526.3157894737,
   "e": "FocusCamera",
   "v": {
	"ease": "CLASSIC",
	"char": 0
}
  },
  {
   "t": 75789.4736842105,
   "e": "FocusCamera",
   "v": {
	"ease": "CLASSIC",
	"char": 1
}
  },
  {
   "t": 77052.6315789474,
   "e": "FocusCamera",
   "v": {
	"ease": "CLASSIC",
	"char": 0
}
  },
  {
   "t": 78157.8947368421,
   "e": "SetCameraBop",
   "v": {
	"rate": 1,
	"intensity": 1,
	"offset": 0
}
  },
  {
   "t": 78315.7894736842,
   "e": "FocusCamera",
   "v": {
	"ease": "CLASSIC",
	"char": 1
}
  },
  {
   "t": 79578.9473684211,
   "e": "FocusCamera",
   "v": {
	"ease": "CLASSIC",
	"char": 2
}
  },
  {
   "t": 80842.1052631579,
   "e": "FocusCamera",
   "v": {
	"ease": "CLASSIC",
	"char": 1
}
  },
  {
   "t": 90947.3684210526,
   "e": "FocusCamera",
   "v": {
	"ease": "CLASSIC",
	"char": 0
}
  },
  {
   "t": 99947.3684210526,
   "e": "SetCameraBop",
   "v": {
	"intensity": 1
}
  },
  {
   "t": 101052.631578947,
   "e": "FocusCamera",
   "v": {
	"ease": "CLASSIC",
	"char": 1
}
  },
  {
   "t": 111157.894736842,
   "e": "FocusCamera",
   "v": {
	"ease": "CLASSIC",
	"char": 0
}
  },
  {
   "t": 121105.263157895,
   "e": "SetCameraBop",
   "v": {
	"rate": 1,
	"intensity": 1
}
  },
  {
   "t": 121263.157894737,
   "e": "FocusCamera",
   "v": {
	"ease": "CLASSIC",
	"char": 1
}
  },
  {
   "t": 126315.789473684,
   "e": "FocusCamera",
   "v": {
	"ease": "CLASSIC",
	"char": 0
}
  },
  {
   "t": 131368.421052631,
   "e": "FocusCamera",
   "v": {
	"ease": "CLASSIC",
	"char": 1
}
  },
  {
   "t": 136421.052631579,
   "e": "FocusCamera",
   "v": {
	"ease": "CLASSIC",
	"char": 0
}
  },
  {
   "t": 139894.736842105,
   "e": "SetCameraBop",
   "v": {
	"rate": 4,
	"intensity": 1
}
  },
  {
   "t": 141473.684210526,
   "e": "FocusCamera",
   "v": {
	"ease": "CLASSIC",
	"char": 1
}
  },
  {
   "t": 144000,
   "e": "FocusCamera",
   "v": {
	"ease": "CLASSIC",
	"char": 0
}
  },
  {
   "t": 146526.315789474,
   "e": "FocusCamera",
   "v": {
	"ease": "CLASSIC",
	"char": 1
}
  },
  {
   "t": 149052.631578947,
   "e": "FocusCamera",
   "v": {
	"ease": "CLASSIC",
	"char": 0
}
  },
  {
   "t": 150631.578947368,
   "e": "SetCameraBop",
   "v": {
	"rate": 1,
	"intensity": 1.5
}
  },
  {
   "t": 150947.368421053,
   "e": "PlayAnimation",
   "v": {
	"anim": "hey",
	"force": true
}
  },
  {
   "t": 151421.052631579,
   "e": "SetCameraBop",
   "v": {
	"rate": 16,
	"intensity": 0
}
  }
 ],
 "notes": {
  "easy": [
   {
    "t": 10105.2631578947,
    "d": 7,
    "l": 0,
    "p": []
   },
   {
    "t": 10736.8421052632,
    "d": 5,
    "l": 0,
    "p": []
   },
   {
    "t": 11368.4210526316,
    "d": 7,
    "l": 0,
    "p": []
   },
   {
    "t": 11684.2105263158,
    "d": 4,
    "l": 0,
    "p": []
   },
   {
    "t": 12000,
    "d": 5,
    "l": 0,
    "p": []
   },
   {
    "t": 12631.5789473684,
    "d": 7,
    "l": 0,
    "p": []
   },
   {
    "t": 13263.1578947368,
    "d": 4,
    "l": 0,
    "p": []
   },
   {
    "t": 13894.7368421053,
    "d": 6,
    "l": 0,
    "p": []
   },
   {
    "t": 14526.3157894737,
    "d": 5,
    "l": 0,
    "p": []
   },
   {
    "t": 15157.8947368421,
    "d": 6,
    "l": 0,
    "p": []
   },
   {
    "t": 15473.6842105263,
    "d": 7,
    "l": 0,
    "p": []
   },
   {
    "t": 15789.4736842105,
    "d": 4,
    "l": 0,
    "p": []
   },
   {
    "t": 16421.0526315789,
    "d": 6,
    "l": 0,
    "p": []
   },
   {
    "t": 16736.8421052632,
    "d": 7,
    "l": 0,
    "p": []
   },
   {
    "t": 17052.6315789474,
    "d": 5,
    "l": 0,
    "p": []
   },
   {
    "t": 17684.2105263158,
    "d": 7,
    "l": 0,
    "p": []
   },
   {
    "t": 17684.2105263158,
    "d": 3,
    "l": 0,
    "p": []
   },
   {
    "t": 18315.7894736842,
    "d": 4,
    "l": 0,
    "p": []
   },
   {
    "t": 18315.7894736842,
    "d": 0,
    "l": 0,
    "p": []
   },
   {
    "t": 18947.3684210526,
    "d": 6,
    "l": 0,
    "p": []
   },
   {
    "t": 18947.3684210526,
    "d": 2,
    "l": 0,
    "p": []
   },
   {
    "t": 19578.9473684211,
    "d": 5,
    "l": 0,
    "p": []
   },
   {
    "t": 19578.9473684211,
    "d": 1,
    "l": 0,
    "p": []
   },
   {
    "t": 20210.5263157895,
    "d": 7,
    "l": 0,
    "p": []
   },
   {
    "t": 20842.1052631579,
    "d": 5,
    "l": 0,
    "p": []
   },
   {
    "t": 21473.6842105263,
    "d": 7,
    "l": 0,
    "p": []
   },
   {
    "t": 22105.2631578947,
    "d": 5,
    "l": 0,
    "p": []
   },
   {
    "t": 22736.8421052632,
    "d": 6,
    "l": 0,
    "p": []
   },
   {
    "t": 23368.4210526316,
    "d": 7,
    "l": 0,
    "p": []
   },
   {
    "t": 24000,
    "d": 4,
    "l": 0,
    "p": []
   },
   {
    "t": 24631.5789473684,
    "d": 5,
    "l": 0,
    "p": []
   },
   {
    "t": 25263.1578947369,
    "d": 3,
    "l": 0,
    "p": []
   },
   {
    "t": 25894.7368421053,
    "d": 1,
    "l": 0,
    "p": []
   },
   {
    "t": 26526.3157894737,
    "d": 3,
    "l": 0,
    "p": []
   },
   {
    "t": 27157.8947368421,
    "d": 1,
    "l": 0,
    "p": []
   },
   {
    "t": 27789.4736842105,
    "d": 2,
    "l": 0,
    "p": []
   },
   {
    "t": 28421.0526315789,
    "d": 3,
    "l": 0,
    "p": []
   },
   {
    "t": 29052.6315789474,
    "d": 0,
    "l": 0,
    "p": []
   },
   {
    "t": 29684.2105263158,
    "d": 1,
    "l": 0,
    "p": []
   },
   {
    "t": 30315.7894736842,
    "d": 7,
    "l": 0,
    "p": []
   },
   {
    "t": 30947.3684210526,
    "d": 4,
    "l": 0,
    "p": []
   },
   {
    "t": 31578.9473684211,
    "d": 6,
    "l": 0,
    "p": []
   },
   {
    "t": 32210.5263157895,
    "d": 5,
    "l": 0,
    "p": []
   },
   {
    "t": 32842.1052631579,
    "d": 7,
    "l": 0,
    "p": []
   },
   {
    "t": 33157.8947368421,
    "d": 7,
    "l": 0,
    "p": []
   },
   {
    "t": 33473.6842105263,
    "d": 7,
    "l": 0,
    "p": []
   },
   {
    "t": 33631.5789473684,
    "d": 7,
    "l": 0,
    "p": []
   },
   {
    "t": 33947.3684210526,
    "d": 7,
    "l": 0,
    "p": []
   },
   {
    "t": 34421.0526315789,
    "d": 5,
    "l": 0,
    "p": []
   },
   {
    "t": 34736.8421052632,
    "d": 6,
    "l": 0,
    "p": []
   },
   {
    "t": 35052.6315789474,
    "d": 4,
    "l": 0,
    "p": []
   },
   {
    "t": 35368.4210526316,
    "d": 3,
    "l": 0,
    "p": []
   },
   {
    "t": 36000,
    "d": 0,
    "l": 0,
    "p": []
   },
   {
    "t": 36631.5789473684,
    "d": 2,
    "l": 0,
    "p": []
   },
   {
    "t": 37263.1578947368,
    "d": 1,
    "l": 0,
    "p": []
   },
   {
    "t": 37894.7368421053,
    "d": 3,
    "l": 0,
    "p": []
   },
   {
    "t": 38210.5263157895,
    "d": 3,
    "l": 0,
    "p": []
   },
   {
    "t": 38526.3157894737,
    "d": 3,
    "l": 0,
    "p": []
   },
   {
    "t": 38684.2105263158,
    "d": 3,
    "l": 0,
    "p": []
   },
   {
    "t": 39000,
    "d": 3,
    "l": 0,
    "p": []
   },
   {
    "t": 39473.6842105263,
    "d": 1,
    "l": 0,
    "p": []
   },
   {
    "t": 39789.4736842105,
    "d": 2,
    "l": 0,
    "p": []
   },
   {
    "t": 40105.2631578947,
    "d": 0,
    "l": 0,
    "p": []
   },
   {
    "t": 40421.0526315789,
    "d": 6,
    "l": 0,
    "p": []
   },
   {
    "t": 41052.6315789474,
    "d": 5,
    "l": 0,
    "p": []
   },
   {
    "t": 41684.2105263158,
    "d": 7,
    "l": 0,
    "p": []
   },
   {
    "t": 41842.1052631579,
    "d": 4,
    "l": 0,
    "p": []
   },
   {
    "t": 42157.8947368421,
    "d": 7,
    "l": 0,
    "p": []
   },
   {
    "t": 42315.7894736842,
    "d": 4,
    "l": 0,
    "p": []
   },
   {
    "t": 42947.3684210526,
    "d": 7,
    "l": 0,
    "p": []
   },
   {
    "t": 43578.9473684211,
    "d": 4,
    "l": 0,
    "p": []
   },
   {
    "t": 44210.5263157895,
    "d": 5,
    "l": 0,
    "p": []
   },
   {
    "t": 44842.1052631579,
    "d": 6,
    "l": 0,
    "p": []
   },
   {
    "t": 45473.6842105263,
    "d": 2,
    "l": 0,
    "p": []
   },
   {
    "t": 46105.2631578947,
    "d": 1,
    "l": 0,
    "p": []
   },
   {
    "t": 46736.8421052632,
    "d": 3,
    "l": 0,
    "p": []
   },
   {
    "t": 46894.7368421053,
    "d": 0,
    "l": 0,
    "p": []
   },
   {
    "t": 47210.5263157895,
    "d": 3,
    "l": 0,
    "p": []
   },
   {
    "t": 47368.4210526316,
    "d": 0,
    "l": 0,
    "p": []
   },
   {
    "t": 48000,
    "d": 3,
    "l": 0,
    "p": []
   },
   {
    "t": 48631.5789473684,
    "d": 0,
    "l": 0,
    "p": []
   },
   {
    "t": 49263.1578947368,
    "d": 1,
    "l": 0,
    "p": []
   },
   {
    "t": 49894.7368421053,
    "d": 2,
    "l": 0,
    "p": []
   },
   {
    "t": 50526.3157894737,
    "d": 4,
    "l": 0,
    "p": []
   },
   {
    "t": 50842.1052631579,
    "d": 7,
    "l": 0,
    "p": []
   },
   {
    "t": 51157.8947368421,
    "d": 4,
    "l": 0,
    "p": []
   },
   {
    "t": 51473.6842105263,
    "d": 7,
    "l": 0,
    "p": []
   },
   {
    "t": 51789.4736842105,
    "d": 4,
    "l": 0,
    "p": []
   },
   {
    "t": 52105.2631578947,
    "d": 7,
    "l": 0,
    "p": []
   },
   {
    "t": 52421.0526315789,
    "d": 4,
    "l": 0,
    "p": []
   },
   {
    "t": 53052.6315789474,
    "d": 5,
    "l": 0,
    "p": []
   },
   {
    "t": 53368.4210526316,
    "d": 6,
    "l": 0,
    "p": []
   },
   {
    "t": 53684.2105263158,
    "d": 5,
    "l": 0,
    "p": []
   },
   {
    "t": 54000,
    "d": 6,
    "l": 0,
    "p": []
   },
   {
    "t": 54315.7894736842,
    "d": 5,
    "l": 0,
    "p": []
   },
   {
    "t": 54631.5789473684,
    "d": 6,
    "l": 0,
    "p": []
   },
   {
    "t": 54947.3684210526,
    "d": 5,
    "l": 0,
    "p": []
   },
   {
    "t": 55578.9473684211,
    "d": 0,
    "l": 0,
    "p": []
   },
   {
    "t": 55894.7368421053,
    "d": 3,
    "l": 0,
    "p": []
   },
   {
    "t": 56210.5263157895,
    "d": 0,
    "l": 0,
    "p": []
   },
   {
    "t": 56526.3157894737,
    "d": 3,
    "l": 0,
    "p": []
   },
   {
    "t": 56842.1052631579,
    "d": 0,
    "l": 0,
    "p": []
   },
   {
    "t": 57157.8947368421,
    "d": 3,
    "l": 0,
    "p": []
   },
   {
    "t": 57473.6842105263,
    "d": 0,
    "l": 0,
    "p": []
   },
   {
    "t": 58105.2631578947,
    "d": 1,
    "l": 0,
    "p": []
   },
   {
    "t": 58421.0526315789,
    "d": 2,
    "l": 0,
    "p": []
   },
   {
    "t": 58736.8421052632,
    "d": 1,
    "l": 0,
    "p": []
   },
   {
    "t": 59052.6315789474,
    "d": 2,
    "l": 0,
    "p": []
   },
   {
    "t": 59368.4210526316,
    "d": 1,
    "l": 0,
    "p": []
   },
   {
    "t": 59684.2105263158,
    "d": 2,
    "l": 0,
    "p": []
   },
   {
    "t": 60000,
    "d": 1,
    "l": 0,
    "p": []
   },
   {
    "t": 60631.5789473684,
    "d": 7,
    "l": 0,
    "p": []
   },
   {
    "t": 60947.3684210526,
    "d": 7,
    "l": 0,
    "p": []
   },
   {
    "t": 61263.1578947368,
    "d": 7,
    "l": 0,
    "p": []
   },
   {
    "t": 61578.9473684211,
    "d": 7,
    "l": 0,
    "p": []
   },
   {
    "t": 61894.7368421053,
    "d": 7,
    "l": 0,
    "p": []
   },
   {
    "t": 62210.5263157895,
    "d": 7,
    "l": 0,
    "p": []
   },
   {
    "t": 62526.3157894737,
    "d": 7,
    "l": 0,
    "p": []
   },
   {
    "t": 62842.1052631579,
    "d": 7,
    "l": 0,
    "p": []
   },
   {
    "t": 63157.8947368421,
    "d": 6,
    "l": 0,
    "p": []
   },
   {
    "t": 63473.6842105263,
    "d": 6,
    "l": 0,
    "p": []
   },
   {
    "t": 63789.4736842105,
    "d": 6,
    "l": 0,
    "p": []
   },
   {
    "t": 64105.2631578947,
    "d": 6,
    "l": 0,
    "p": []
   },
   {
    "t": 64421.0526315789,
    "d": 6,
    "l": 0,
    "p": []
   },
   {
    "t": 64736.8421052632,
    "d": 6,
    "l": 0,
    "p": []
   },
   {
    "t": 65052.6315789474,
    "d": 6,
    "l": 0,
    "p": []
   },
   {
    "t": 65368.4210526316,
    "d": 6,
    "l": 0,
    "p": []
   },
   {
    "t": 65684.2105263158,
    "d": 3,
    "l": 0,
    "p": []
   },
   {
    "t": 66000,
    "d": 3,
    "l": 0,
    "p": []
   },
   {
    "t": 66315.7894736842,
    "d": 3,
    "l": 0,
    "p": []
   },
   {
    "t": 66631.5789473684,
    "d": 3,
    "l": 0,
    "p": []
   },
   {
    "t": 66947.3684210526,
    "d": 3,
    "l": 0,
    "p": []
   },
   {
    "t": 67263.1578947368,
    "d": 3,
    "l": 0,
    "p": []
   },
   {
    "t": 67578.9473684211,
    "d": 3,
    "l": 0,
    "p": []
   },
   {
    "t": 67894.7368421053,
    "d": 3,
    "l": 0,
    "p": []
   },
   {
    "t": 68210.5263157895,
    "d": 2,
    "l": 0,
    "p": []
   },
   {
    "t": 68526.3157894737,
    "d": 2,
    "l": 0,
    "p": []
   },
   {
    "t": 68842.1052631579,
    "d": 2,
    "l": 0,
    "p": []
   },
   {
    "t": 69157.8947368421,
    "d": 2,
    "l": 0,
    "p": []
   },
   {
    "t": 69473.6842105263,
    "d": 2,
    "l": 0,
    "p": []
   },
   {
    "t": 69789.4736842105,
    "d": 2,
    "l": 0,
    "p": []
   },
   {
    "t": 70105.2631578947,
    "d": 2,
    "l": 0,
    "p": []
   },
   {
    "t": 70421.0526315789,
    "d": 2,
    "l": 0,
    "p": []
   },
   {
    "t": 70736.8421052632,
    "d": 6,
    "l": 0,
    "p": []
   },
   {
    "t": 71210.5263157895,
    "d": 7,
    "l": 0,
    "p": []
   },
   {
    "t": 71684.2105263158,
    "d": 5,
    "l": 0,
    "p": []
   },
   {
    "t": 72000,
    "d": 2,
    "l": 0,
    "p": []
   },
   {
    "t": 72473.6842105263,
    "d": 3,
    "l": 0,
    "p": []
   },
   {
    "t": 72947.3684210526,
    "d": 1,
    "l": 0,
    "p": []
   },
   {
    "t": 73263.1578947368,
    "d": 4,
    "l": 0,
    "p": []
   },
   {
    "t": 73736.8421052632,
    "d": 7,
    "l": 0,
    "p": []
   },
   {
    "t": 74210.5263157895,
    "d": 5,
    "l": 0,
    "p": []
   },
   {
    "t": 74526.3157894737,
    "d": 0,
    "l": 0,
    "p": []
   },
   {
    "t": 75000,
    "d": 3,
    "l": 0,
    "p": []
   },
   {
    "t": 75473.6842105263,
    "d": 1,
    "l": 0,
    "p": []
   },
   {
    "t": 75789.4736842105,
    "d": 7,
    "l": 0,
    "p": []
   },
   {
    "t": 76421.0526315789,
    "d": 4,
    "l": 0,
    "p": []
   },
   {
    "t": 77052.6315789474,
    "d": 3,
    "l": 0,
    "p": []
   },
   {
    "t": 77684.2105263158,
    "d": 0,
    "l": 0,
    "p": []
   },
   {
    "t": 78315.7894736842,
    "d": 7,
    "l": 0,
    "p": []
   },
   {
    "t": 78947.3684210526,
    "d": 4,
    "l": 0,
    "p": []
   },
   {
    "t": 79578.9473684211,
    "d": 3,
    "l": 0,
    "p": []
   },
   {
    "t": 79578.9473684211,
    "d": 7,
    "l": 0,
    "p": []
   },
   {
    "t": 80210.5263157895,
    "d": 4,
    "l": 0,
    "p": []
   },
   {
    "t": 80210.5263157895,
    "d": 0,
    "l": 0,
    "p": []
   },
   {
    "t": 80842.1052631579,
    "d": 5,
    "l": 0,
    "p": []
   },
   {
    "t": 81473.6842105263,
    "d": 7,
    "l": 0,
    "p": []
   },
   {
    "t": 82105.2631578947,
    "d": 4,
    "l": 0,
    "p": []
   },
   {
    "t": 82736.8421052632,
    "d": 6,
    "l": 0,
    "p": []
   },
   {
    "t": 83368.4210526316,
    "d": 7,
    "l": 0,
    "p": []
   },
   {
    "t": 84000,
    "d": 4,
    "l": 0,
    "p": []
   },
   {
    "t": 84631.5789473684,
    "d": 6,
    "l": 0,
    "p": []
   },
   {
    "t": 85263.1578947368,
    "d": 5,
    "l": 0,
    "p": []
   },
   {
    "t": 85894.7368421053,
    "d": 4,
    "l": 0,
    "p": []
   },
   {
    "t": 86526.3157894737,
    "d": 6,
    "l": 0,
    "p": []
   },
   {
    "t": 87157.8947368421,
    "d": 5,
    "l": 0,
    "p": []
   },
   {
    "t": 87789.4736842105,
    "d": 7,
    "l": 0,
    "p": []
   },
   {
    "t": 88421.0526315789,
    "d": 6,
    "l": 0,
    "p": []
   },
   {
    "t": 89052.6315789474,
    "d": 5,
    "l": 0,
    "p": []
   },
   {
    "t": 89684.2105263158,
    "d": 7,
    "l": 0,
    "p": []
   },
   {
    "t": 90315.7894736842,
    "d": 4,
    "l": 0,
    "p": []
   },
   {
    "t": 90947.3684210526,
    "d": 1,
    "l": 0,
    "p": []
   },
   {
    "t": 91578.9473684211,
    "d": 3,
    "l": 0,
    "p": []
   },
   {
    "t": 92210.5263157895,
    "d": 0,
    "l": 0,
    "p": []
   },
   {
    "t": 92842.1052631579,
    "d": 2,
    "l": 0,
    "p": []
   },
   {
    "t": 93473.6842105263,
    "d": 3,
    "l": 0,
    "p": []
   },
   {
    "t": 94105.2631578947,
    "d": 0,
    "l": 0,
    "p": []
   },
   {
    "t": 94736.8421052631,
    "d": 2,
    "l": 0,
    "p": []
   },
   {
    "t": 95368.4210526316,
    "d": 1,
    "l": 0,
    "p": []
   },
   {
    "t": 96000,
    "d": 0,
    "l": 0,
    "p": []
   },
   {
    "t": 96631.5789473684,
    "d": 2,
    "l": 0,
    "p": []
   },
   {
    "t": 97263.1578947368,
    "d": 1,
    "l": 0,
    "p": []
   },
   {
    "t": 97894.7368421053,
    "d": 3,
    "l": 0,
    "p": []
   },
   {
    "t": 98526.3157894737,
    "d": 2,
    "l": 0,
    "p": []
   },
   {
    "t": 99157.8947368421,
    "d": 1,
    "l": 0,
    "p": []
   },
   {
    "t": 99789.4736842105,
    "d": 3,
    "l": 0,
    "p": []
   },
   {
    "t": 100421.052631579,
    "d": 0,
    "l": 0,
    "p": []
   },
   {
    "t": 101052.631578947,
    "d": 7,
    "l": 0,
    "p": []
   },
   {
    "t": 101684.210526316,
    "d": 5,
    "l": 0,
    "p": []
   },
   {
    "t": 102315.789473684,
    "d": 7,
    "l": 0,
    "p": []
   },
   {
    "t": 102631.578947368,
    "d": 4,
    "l": 0,
    "p": []
   },
   {
    "t": 102947.368421053,
    "d": 5,
    "l": 0,
    "p": []
   },
   {
    "t": 103578.947368421,
    "d": 7,
    "l": 0,
    "p": []
   },
   {
    "t": 104210.526315789,
    "d": 4,
    "l": 0,
    "p": []
   },
   {
    "t": 104842.105263158,
    "d": 6,
    "l": 0,
    "p": []
   },
   {
    "t": 105473.684210526,
    "d": 5,
    "l": 0,
    "p": []
   },
   {
    "t": 106105.263157895,
    "d": 6,
    "l": 0,
    "p": []
   },
   {
    "t": 106421.052631579,
    "d": 7,
    "l": 0,
    "p": []
   },
   {
    "t": 106736.842105263,
    "d": 4,
    "l": 0,
    "p": []
   },
   {
    "t": 107368.421052632,
    "d": 6,
    "l": 0,
    "p": []
   },
   {
    "t": 107684.210526316,
    "d": 7,
    "l": 0,
    "p": []
   },
   {
    "t": 108000,
    "d": 5,
    "l": 0,
    "p": []
   },
   {
    "t": 108631.578947368,
    "d": 7,
    "l": 0,
    "p": []
   },
   {
    "t": 109263.157894737,
    "d": 4,
    "l": 0,
    "p": []
   },
   {
    "t": 109894.736842105,
    "d": 6,
    "l": 0,
    "p": []
   },
   {
    "t": 110526.315789474,
    "d": 5,
    "l": 0,
    "p": []
   },
   {
    "t": 111157.894736842,
    "d": 3,
    "l": 0,
    "p": []
   },
   {
    "t": 111789.473684211,
    "d": 1,
    "l": 0,
    "p": []
   },
   {
    "t": 112421.052631579,
    "d": 3,
    "l": 0,
    "p": []
   },
   {
    "t": 112736.842105263,
    "d": 0,
    "l": 0,
    "p": []
   },
   {
    "t": 113052.631578947,
    "d": 1,
    "l": 0,
    "p": []
   },
   {
    "t": 113684.210526316,
    "d": 3,
    "l": 0,
    "p": []
   },
   {
    "t": 114315.789473684,
    "d": 0,
    "l": 0,
    "p": []
   },
   {
    "t": 114947.368421053,
    "d": 2,
    "l": 0,
    "p": []
   },
   {
    "t": 115578.947368421,
    "d": 1,
    "l": 0,
    "p": []
   },
   {
    "t": 116210.526315789,
    "d": 2,
    "l": 0,
    "p": []
   },
   {
    "t": 116526.315789474,
    "d": 3,
    "l": 0,
    "p": []
   },
   {
    "t": 116842.105263158,
    "d": 0,
    "l": 0,
    "p": []
   },
   {
    "t": 117473.684210526,
    "d": 2,
    "l": 0,
    "p": []
   },
   {
    "t": 117789.473684211,
    "d": 3,
    "l": 0,
    "p": []
   },
   {
    "t": 118105.263157895,
    "d": 1,
    "l": 0,
    "p": []
   },
   {
    "t": 118736.842105263,
    "d": 3,
    "l": 0,
    "p": []
   },
   {
    "t": 119368.421052632,
    "d": 0,
    "l": 0,
    "p": []
   },
   {
    "t": 120000,
    "d": 2,
    "l": 0,
    "p": []
   },
   {
    "t": 120631.578947368,
    "d": 1,
    "l": 0,
    "p": []
   },
   {
    "t": 121263.157894737,
    "d": 7,
    "l": 0,
    "p": []
   },
   {
    "t": 121894.736842105,
    "d": 5,
    "l": 0,
    "p": []
   },
   {
    "t": 122526.315789474,
    "d": 7,
    "l": 0,
    "p": []
   },
   {
    "t": 123157.894736842,
    "d": 5,
    "l": 0,
    "p": []
   },
   {
    "t": 123789.473684211,
    "d": 6,
    "l": 0,
    "p": []
   },
   {
    "t": 124421.052631579,
    "d": 7,
    "l": 0,
    "p": []
   },
   {
    "t": 125052.631578947,
    "d": 4,
    "l": 0,
    "p": []
   },
   {
    "t": 125684.210526316,
    "d": 5,
    "l": 0,
    "p": []
   },
   {
    "t": 126315.789473684,
    "d": 3,
    "l": 0,
    "p": []
   },
   {
    "t": 126947.368421053,
    "d": 1,
    "l": 0,
    "p": []
   },
   {
    "t": 127578.947368421,
    "d": 3,
    "l": 0,
    "p": []
   },
   {
    "t": 128210.526315789,
    "d": 1,
    "l": 0,
    "p": []
   },
   {
    "t": 128842.105263158,
    "d": 2,
    "l": 0,
    "p": []
   },
   {
    "t": 129473.684210526,
    "d": 3,
    "l": 0,
    "p": []
   },
   {
    "t": 130105.263157895,
    "d": 0,
    "l": 0,
    "p": []
   },
   {
    "t": 130736.842105263,
    "d": 1,
    "l": 0,
    "p": []
   },
   {
    "t": 131368.421052632,
    "d": 7,
    "l": 0,
    "p": []
   },
   {
    "t": 132000,
    "d": 4,
    "l": 0,
    "p": []
   },
   {
    "t": 132631.578947368,
    "d": 6,
    "l": 0,
    "p": []
   },
   {
    "t": 133263.157894737,
    "d": 5,
    "l": 0,
    "p": []
   },
   {
    "t": 133894.736842105,
    "d": 7,
    "l": 0,
    "p": []
   },
   {
    "t": 134210.526315789,
    "d": 7,
    "l": 0,
    "p": []
   },
   {
    "t": 134526.315789474,
    "d": 7,
    "l": 0,
    "p": []
   },
   {
    "t": 134684.210526316,
    "d": 7,
    "l": 0,
    "p": []
   },
   {
    "t": 135000,
    "d": 7,
    "l": 0,
    "p": []
   },
   {
    "t": 135473.684210526,
    "d": 5,
    "l": 0,
    "p": []
   },
   {
    "t": 135789.473684211,
    "d": 6,
    "l": 0,
    "p": []
   },
   {
    "t": 136105.263157895,
    "d": 4,
    "l": 0,
    "p": []
   },
   {
    "t": 136421.052631579,
    "d": 3,
    "l": 0,
    "p": []
   },
   {
    "t": 137052.631578947,
    "d": 0,
    "l": 0,
    "p": []
   },
   {
    "t": 137684.210526316,
    "d": 2,
    "l": 0,
    "p": []
   },
   {
    "t": 138315.789473684,
    "d": 1,
    "l": 0,
    "p": []
   },
   {
    "t": 138947.368421053,
    "d": 3,
    "l": 0,
    "p": []
   },
   {
    "t": 139263.157894737,
    "d": 3,
    "l": 0,
    "p": []
   },
   {
    "t": 139578.947368421,
    "d": 3,
    "l": 0,
    "p": []
   },
   {
    "t": 139736.842105263,
    "d": 3,
    "l": 0,
    "p": []
   },
   {
    "t": 140052.631578947,
    "d": 3,
    "l": 0,
    "p": []
   },
   {
    "t": 140526.315789474,
    "d": 1,
    "l": 0,
    "p": []
   },
   {
    "t": 140842.105263158,
    "d": 2,
    "l": 0,
    "p": []
   },
   {
    "t": 141157.894736842,
    "d": 0,
    "l": 0,
    "p": []
   }
  ],
  "hard": [
   {
    "t": 10105.2631578947,
    "d": 7,
    "l": 157.894736842105,
    "p": []
   },
   {
    "t": 10421.0526315789,
    "d": 4,
    "l": 157.894736842105,
    "p": []
   },
   {
    "t": 10736.8421052632,
    "d": 5,
    "l": 157.894736842105,
    "p": []
   },
   {
    "t": 11052.6315789474,
    "d": 6,
    "l": 157.894736842105,
    "p": []
   },
   {
    "t": 11368.4210526316,
    "d": 7,
    "l": 157.894736842105,
    "p": []
   },
   {
    "t": 11684.2105263158,
    "d": 4,
    "l": 157.894736842105,
    "p": []
   },
   {
    "t": 12000,
    "d": 5,
    "l": 473.684210526316,
    "p": []
   },
   {
    "t": 12631.5789473684,
    "d": 7,
    "l": 157.894736842105,
    "p": []
   },
   {
    "t": 12947.3684210526,
    "d": 4,
    "l": 157.894736842105,
    "p": []
   },
   {
    "t": 13263.1578947368,
    "d": 7,
    "l": 157.894736842105,
    "p": []
   },
   {
    "t": 13578.9473684211,
    "d": 5,
    "l": 157.894736842105,
    "p": []
   },
   {
    "t": 13894.7368421053,
    "d": 6,
    "l": 473.684210526316,
    "p": []
   },
   {
    "t": 14526.3157894737,
    "d": 5,
    "l": 473.684210526316,
    "p": []
   },
   {
    "t": 15157.8947368421,
    "d": 6,
    "l": 157.894736842105,
    "p": []
   },
   {
    "t": 15473.6842105263,
    "d": 7,
    "l": 157.894736842105,
    "p": []
   },
   {
    "t": 15789.4736842105,
    "d": 4,
    "l": 473.684210526316,
    "p": []
   },
   {
    "t": 16421.0526315789,
    "d": 6,
    "l": 157.894736842105,
    "p": []
   },
   {
    "t": 16736.8421052632,
    "d": 7,
    "l": 157.894736842105,
    "p": []
   },
   {
    "t": 17052.6315789474,
    "d": 5,
    "l": 473.684210526316,
    "p": []
   },
   {
    "t": 17684.2105263158,
    "d": 3,
    "l": 473.684210526316,
    "p": []
   },
   {
    "t": 17684.2105263158,
    "d": 7,
    "l": 473.684210526316,
    "p": []
   },
   {
    "t": 18315.7894736842,
    "d": 0,
    "l": 473.684210526316,
    "p": []
   },
   {
    "t": 18315.7894736842,
    "d": 4,
    "l": 473.684210526316,
    "p": []
   },
   {
    "t": 18947.3684210526,
    "d": 2,
    "l": 473.684210526316,
    "p": []
   },
   {
    "t": 18947.3684210526,
    "d": 6,
    "l": 473.684210526316,
    "p": []
   },
   {
    "t": 19578.9473684211,
    "d": 1,
    "l": 473.684210526316,
    "p": []
   },
   {
    "t": 19578.9473684211,
    "d": 5,
    "l": 473.684210526316,
    "p": []
   },
   {
    "t": 19736.8421052632,
    "d": 4,
    "l": 0,
    "p": []
   },
   {
    "t": 20210.5263157895,
    "d": 7,
    "l": 157.894736842105,
    "p": []
   },
   {
    "t": 20526.3157894737,
    "d": 5,
    "l": 157.894736842105,
    "p": []
   },
   {
    "t": 20842.1052631579,
    "d": 7,
    "l": 0,
    "p": []
   },
   {
    "t": 21000,
    "d": 5,
    "l": 157.894736842105,
    "p": []
   },
   {
    "t": 21315.7894736842,
    "d": 7,
    "l": 0,
    "p": []
   },
   {
    "t": 21473.6842105263,
    "d": 5,
    "l": 157.894736842105,
    "p": []
   },
   {
    "t": 21789.4736842105,
    "d": 4,
    "l": 157.894736842105,
    "p": []
   },
   {
    "t": 22105.2631578947,
    "d": 6,
    "l": 157.894736842105,
    "p": []
   },
   {
    "t": 22421.0526315789,
    "d": 5,
    "l": 157.894736842105,
    "p": []
   },
   {
    "t": 22736.8421052632,
    "d": 6,
    "l": 157.894736842105,
    "p": []
   },
   {
    "t": 23052.6315789474,
    "d": 7,
    "l": 157.894736842105,
    "p": []
   },
   {
    "t": 23368.4210526316,
    "d": 4,
    "l": 157.894736842105,
    "p": []
   },
   {
    "t": 23684.2105263158,
    "d": 5,
    "l": 157.894736842105,
    "p": []
   },
   {
    "t": 24000,
    "d": 7,
    "l": 473.684210526316,
    "p": []
   },
   {
    "t": 24631.5789473684,
    "d": 4,
    "l": 473.684210526316,
    "p": []
   },
   {
    "t": 25263.1578947368,
    "d": 3,
    "l": 157.894736842105,
    "p": []
   },
   {
    "t": 25578.9473684211,
    "d": 1,
    "l": 157.894736842105,
    "p": []
   },
   {
    "t": 25894.7368421053,
    "d": 3,
    "l": 0,
    "p": []
   },
   {
    "t": 26052.6315789474,
    "d": 1,
    "l": 157.894736842105,
    "p": []
   },
   {
    "t": 26368.4210526316,
    "d": 3,
    "l": 0,
    "p": []
   },
   {
    "t": 26526.3157894737,
    "d": 1,
    "l": 157.894736842105,
    "p": []
   },
   {
    "t": 26842.1052631579,
    "d": 0,
    "l": 157.894736842105,
    "p": []
   },
   {
    "t": 27157.8947368421,
    "d": 2,
    "l": 157.894736842105,
    "p": []
   },
   {
    "t": 27473.6842105263,
    "d": 1,
    "l": 157.894736842105,
    "p": []
   },
   {
    "t": 27789.4736842105,
    "d": 2,
    "l": 157.894736842105,
    "p": []
   },
   {
    "t": 28105.2631578947,
    "d": 3,
    "l": 157.894736842105,
    "p": []
   },
   {
    "t": 28421.0526315789,
    "d": 0,
    "l": 157.894736842105,
    "p": []
   },
   {
    "t": 28736.8421052632,
    "d": 1,
    "l": 157.894736842105,
    "p": []
   },
   {
    "t": 29052.6315789474,
    "d": 3,
    "l": 473.684210526316,
    "p": []
   },
   {
    "t": 29684.2105263158,
    "d": 0,
    "l": 473.684210526316,
    "p": []
   },
   {
    "t": 30315.7894736842,
    "d": 7,
    "l": 315.789473684211,
    "p": []
   },
   {
    "t": 30789.4736842105,
    "d": 6,
    "l": 0,
    "p": []
   },
   {
    "t": 30947.3684210526,
    "d": 4,
    "l": 315.789473684211,
    "p": []
   },
   {
    "t": 31421.0526315789,
    "d": 5,
    "l": 0,
    "p": []
   },
   {
    "t": 31578.9473684211,
    "d": 7,
    "l": 157.894736842105,
    "p": []
   },
   {
    "t": 31894.7368421053,
    "d": 4,
    "l": 157.894736842105,
    "p": []
   },
   {
    "t": 32210.5263157895,
    "d": 6,
    "l": 157.894736842105,
    "p": []
   },
   {
    "t": 32526.3157894737,
    "d": 5,
    "l": 157.894736842105,
    "p": []
   },
   {
    "t": 32842.1052631579,
    "d": 7,
    "l": 157.894736842105,
    "p": []
   },
   {
    "t": 33157.8947368421,
    "d": 4,
    "l": 157.894736842101,
    "p": []
   },
   {
    "t": 33473.6842105263,
    "d": 7,
    "l": 0,
    "p": []
   },
   {
    "t": 33631.5789473684,
    "d": 6,
    "l": 157.894736842105,
    "p": []
   },
   {
    "t": 33947.3684210526,
    "d": 5,
    "l": 315.789473684211,
    "p": []
   },
   {
    "t": 34421.0526315789,
    "d": 7,
    "l": 157.894736842105,
    "p": []
   },
   {
    "t": 34736.8421052632,
    "d": 4,
    "l": 157.894736842096,
    "p": []
   },
   {
    "t": 35052.6315789474,
    "d": 6,
    "l": 157.894736842105,
    "p": []
   },
   {
    "t": 35368.4210526316,
    "d": 3,
    "l": 315.789473684211,
    "p": []
   },
   {
    "t": 35842.1052631579,
    "d": 2,
    "l": 0,
    "p": []
   },
   {
    "t": 36000,
    "d": 0,
    "l": 315.789473684211,
    "p": []
   },
   {
    "t": 36473.6842105263,
    "d": 1,
    "l": 0,
    "p": []
   },
   {
    "t": 36631.5789473684,
    "d": 3,
    "l": 157.894736842105,
    "p": []
   },
   {
    "t": 36947.3684210526,
    "d": 0,
    "l": 157.894736842096,
    "p": []
   },
   {
    "t": 37263.1578947368,
    "d": 2,
    "l": 157.894736842105,
    "p": []
   },
   {
    "t": 37578.9473684211,
    "d": 1,
    "l": 157.89473684211,
    "p": []
   },
   {
    "t": 37894.7368421053,
    "d": 3,
    "l": 157.89473684211,
    "p": []
   },
   {
    "t": 38210.5263157895,
    "d": 0,
    "l": 0,
    "p": []
   },
   {
    "t": 38526.3157894737,
    "d": 3,
    "l": 0,
    "p": []
   },
   {
    "t": 38684.2105263158,
    "d": 2,
    "l": 0,
    "p": []
   },
   {
    "t": 39000,
    "d": 1,
    "l": 315.789473684211,
    "p": []
   },
   {
    "t": 39473.6842105263,
    "d": 3,
    "l": 0,
    "p": []
   },
   {
    "t": 39789.4736842105,
    "d": 0,
    "l": 157.89473684211,
    "p": []
   },
   {
    "t": 40105.2631578947,
    "d": 2,
    "l": 157.89473684211,
    "p": []
   },
   {
    "t": 40421.0526315789,
    "d": 6,
    "l": 157.894736842105,
    "p": []
   },
   {
    "t": 40736.8421052632,
    "d": 7,
    "l": 157.894736842105,
    "p": []
   },
   {
    "t": 41052.6315789474,
    "d": 4,
    "l": 157.894736842105,
    "p": []
   },
   {
    "t": 41368.4210526316,
    "d": 5,
    "l": 157.894736842105,
    "p": []
   },
   {
    "t": 41684.2105263158,
    "d": 6,
    "l": 0,
    "p": []
   },
   {
    "t": 41842.1052631579,
    "d": 5,
    "l": 157.894736842105,
    "p": []
   },
   {
    "t": 42157.8947368421,
    "d": 6,
    "l": 0,
    "p": []
   },
   {
    "t": 42315.7894736842,
    "d": 5,
    "l": 473.684210526316,
    "p": []
   },
   {
    "t": 42947.3684210526,
    "d": 7,
    "l": 157.894736842105,
    "p": []
   },
   {
    "t": 43263.1578947368,
    "d": 4,
    "l": 157.894736842105,
    "p": []
   },
   {
    "t": 43578.9473684211,
    "d": 6,
    "l": 157.894736842105,
    "p": []
   },
   {
    "t": 43894.7368421053,
    "d": 5,
    "l": 157.894736842105,
    "p": []
   },
   {
    "t": 44210.5263157895,
    "d": 7,
    "l": 157.894736842105,
    "p": []
   },
   {
    "t": 44526.3157894737,
    "d": 4,
    "l": 157.894736842105,
    "p": []
   },
   {
    "t": 44842.1052631579,
    "d": 6,
    "l": 157.894736842105,
    "p": []
   },
   {
    "t": 45157.8947368421,
    "d": 5,
    "l": 157.894736842105,
    "p": []
   },
   {
    "t": 45473.6842105263,
    "d": 2,
    "l": 0,
    "p": []
   },
   {
    "t": 45789.4736842105,
    "d": 3,
    "l": 0,
    "p": []
   },
   {
    "t": 46105.2631578947,
    "d": 0,
    "l": 0,
    "p": []
   },
   {
    "t": 46421.0526315789,
    "d": 1,
    "l": 0,
    "p": []
   },
   {
    "t": 46736.8421052632,
    "d": 2,
    "l": 0,
    "p": []
   },
   {
    "t": 46894.7368421053,
    "d": 1,
    "l": 157.894736842105,
    "p": []
   },
   {
    "t": 47210.5263157895,
    "d": 2,
    "l": 0,
    "p": []
   },
   {
    "t": 47368.4210526316,
    "d": 1,
    "l": 473.684210526316,
    "p": []
   },
   {
    "t": 48000,
    "d": 3,
    "l": 157.894736842105,
    "p": []
   },
   {
    "t": 48315.7894736842,
    "d": 0,
    "l": 157.894736842105,
    "p": []
   },
   {
    "t": 48631.5789473684,
    "d": 2,
    "l": 157.894736842105,
    "p": []
   },
   {
    "t": 48947.3684210526,
    "d": 1,
    "l": 157.894736842105,
    "p": []
   },
   {
    "t": 49263.1578947368,
    "d": 3,
    "l": 157.894736842105,
    "p": []
   },
   {
    "t": 49578.9473684211,
    "d": 0,
    "l": 157.894736842105,
    "p": []
   },
   {
    "t": 49894.7368421053,
    "d": 2,
    "l": 157.894736842105,
    "p": []
   },
   {
    "t": 50210.5263157895,
    "d": 1,
    "l": 157.894736842105,
    "p": []
   },
   {
    "t": 50526.3157894737,
    "d": 4,
    "l": 157.894736842105,
    "p": []
   },
   {
    "t": 50842.1052631579,
    "d": 7,
    "l": 157.894736842105,
    "p": []
   },
   {
    "t": 51157.8947368421,
    "d": 4,
    "l": 157.894736842105,
    "p": []
   },
   {
    "t": 51473.6842105263,
    "d": 6,
    "l": 157.894736842105,
    "p": []
   },
   {
    "t": 51789.4736842105,
    "d": 5,
    "l": 157.894736842105,
    "p": []
   },
   {
    "t": 52105.2631578947,
    "d": 7,
    "l": 157.894736842105,
    "p": []
   },
   {
    "t": 52421.0526315789,
    "d": 5,
    "l": 473.684210526316,
    "p": []
   },
   {
    "t": 53052.6315789474,
    "d": 4,
    "l": 157.894736842105,
    "p": []
   },
   {
    "t": 53368.4210526316,
    "d": 7,
    "l": 157.894736842105,
    "p": []
   },
   {
    "t": 53684.2105263158,
    "d": 4,
    "l": 157.894736842105,
    "p": []
   },
   {
    "t": 54000,
    "d": 6,
    "l": 157.894736842105,
    "p": []
   },
   {
    "t": 54315.7894736842,
    "d": 7,
    "l": 157.894736842105,
    "p": []
   },
   {
    "t": 54631.5789473684,
    "d": 5,
    "l": 157.894736842123,
    "p": []
   },
   {
    "t": 54947.3684210526,
    "d": 6,
    "l": 473.684210526316,
    "p": []
   },
   {
    "t": 55578.9473684211,
    "d": 0,
    "l": 0,
    "p": []
   },
   {
    "t": 55894.7368421053,
    "d": 3,
    "l": 0,
    "p": []
   },
   {
    "t": 56210.5263157895,
    "d": 1,
    "l": 0,
    "p": []
   },
   {
    "t": 56210.5263157895,
    "d": 0,
    "l": 0,
    "p": []
   },
   {
    "t": 56526.3157894737,
    "d": 2,
    "l": 157.894736842105,
    "p": []
   },
   {
    "t": 56842.1052631579,
    "d": 1,
    "l": 157.894736842105,
    "p": []
   },
   {
    "t": 57157.8947368421,
    "d": 3,
    "l": 157.894736842105,
    "p": []
   },
   {
    "t": 57473.6842105263,
    "d": 1,
    "l": 473.684210526316,
    "p": []
   },
   {
    "t": 58105.2631578947,
    "d": 0,
    "l": 0,
    "p": []
   },
   {
    "t": 58105.2631578947,
    "d": 2,
    "l": 0,
    "p": []
   },
   {
    "t": 58421.0526315789,
    "d": 3,
    "l": 0,
    "p": []
   },
   {
    "t": 58736.8421052632,
    "d": 1,
    "l": 0,
    "p": []
   },
   {
    "t": 59052.6315789474,
    "d": 2,
    "l": 0,
    "p": []
   },
   {
    "t": 59368.4210526316,
    "d": 3,
    "l": 0,
    "p": []
   },
   {
    "t": 59684.2105263158,
    "d": 1,
    "l": 0,
    "p": []
   },
   {
    "t": 60000,
    "d": 2,
    "l": 157.894736842105,
    "p": []
   },
   {
    "t": 60631.5789473684,
    "d": 5,
    "l": 0,
    "p": []
   },
   {
    "t": 60947.3684210526,
    "d": 5,
    "l": 0,
    "p": []
   },
   {
    "t": 61263.1578947368,
    "d": 5,
    "l": 0,
    "p": []
   },
   {
    "t": 61578.9473684211,
    "d": 5,
    "l": 0,
    "p": []
   },
   {
    "t": 61894.7368421053,
    "d": 6,
    "l": 0,
    "p": []
   },
   {
    "t": 62210.5263157895,
    "d": 5,
    "l": 0,
    "p": []
   },
   {
    "t": 62526.3157894737,
    "d": 6,
    "l": 0,
    "p": []
   },
   {
    "t": 62842.1052631579,
    "d": 4,
    "l": 0,
    "p": []
   },
   {
    "t": 63157.8947368421,
    "d": 7,
    "l": 0,
    "p": []
   },
   {
    "t": 63473.6842105263,
    "d": 4,
    "l": 0,
    "p": []
   },
   {
    "t": 63789.4736842105,
    "d": 7,
    "l": 0,
    "p": []
   },
   {
    "t": 64105.2631578947,
    "d": 4,
    "l": 0,
    "p": []
   },
   {
    "t": 64421.0526315789,
    "d": 6,
    "l": 0,
    "p": []
   },
   {
    "t": 64736.8421052632,
    "d": 5,
    "l": 0,
    "p": []
   },
   {
    "t": 65052.6315789474,
    "d": 4,
    "l": 0,
    "p": []
   },
   {
    "t": 65368.4210526316,
    "d": 7,
    "l": 0,
    "p": []
   },
   {
    "t": 65684.2105263158,
    "d": 1,
    "l": 0,
    "p": []
   },
   {
    "t": 66000,
    "d": 1,
    "l": 0,
    "p": []
   },
   {
    "t": 66315.7894736842,
    "d": 1,
    "l": 0,
    "p": []
   },
   {
    "t": 66631.5789473684,
    "d": 1,
    "l": 0,
    "p": []
   },
   {
    "t": 66947.3684210526,
    "d": 2,
    "l": 0,
    "p": []
   },
   {
    "t": 67263.1578947368,
    "d": 1,
    "l": 0,
    "p": []
   },
   {
    "t": 67578.9473684211,
    "d": 3,
    "l": 0,
    "p": []
   },
   {
    "t": 67894.7368421053,
    "d": 1,
    "l": 0,
    "p": []
   },
   {
    "t": 68210.5263157895,
    "d": 3,
    "l": 0,
    "p": []
   },
   {
    "t": 68526.3157894737,
    "d": 0,
    "l": 0,
    "p": []
   },
   {
    "t": 68842.1052631579,
    "d": 3,
    "l": 0,
    "p": []
   },
   {
    "t": 69157.8947368421,
    "d": 0,
    "l": 0,
    "p": []
   },
   {
    "t": 69473.6842105263,
    "d": 2,
    "l": 0,
    "p": []
   },
   {
    "t": 69789.4736842105,
    "d": 1,
    "l": 0,
    "p": []
   },
   {
    "t": 70105.2631578947,
    "d": 0,
    "l": 0,
    "p": []
   },
   {
    "t": 70421.0526315789,
    "d": 3,
    "l": 0,
    "p": []
   },
   {
    "t": 70736.8421052632,
    "d": 6,
    "l": 315.789473684211,
    "p": []
   },
   {
    "t": 71210.5263157895,
    "d": 7,
    "l": 315.789473684211,
    "p": []
   },
   {
    "t": 71684.2105263158,
    "d": 5,
    "l": 157.894736842105,
    "p": []
   },
   {
    "t": 72000,
    "d": 2,
    "l": 315.789473684211,
    "p": []
   },
   {
    "t": 72473.6842105263,
    "d": 3,
    "l": 315.789473684211,
    "p": []
   },
   {
    "t": 72947.3684210526,
    "d": 1,
    "l": 157.894736842105,
    "p": []
   },
   {
    "t": 73263.1578947368,
    "d": 4,
    "l": 315.789473684211,
    "p": []
   },
   {
    "t": 73736.8421052632,
    "d": 7,
    "l": 315.789473684211,
    "p": []
   },
   {
    "t": 74210.5263157895,
    "d": 5,
    "l": 157.894736842105,
    "p": []
   },
   {
    "t": 74526.3157894737,
    "d": 0,
    "l": 315.789473684211,
    "p": []
   },
   {
    "t": 75000,
    "d": 3,
    "l": 315.789473684211,
    "p": []
   },
   {
    "t": 75473.6842105263,
    "d": 1,
    "l": 157.894736842105,
    "p": []
   },
   {
    "t": 75789.4736842105,
    "d": 7,
    "l": 157.894736842114,
    "p": []
   },
   {
    "t": 76105.2631578947,
    "d": 4,
    "l": 157.894736842105,
    "p": []
   },
   {
    "t": 76421.0526315789,
    "d": 5,
    "l": 157.894736842105,
    "p": []
   },
   {
    "t": 76736.8421052632,
    "d": 6,
    "l": 157.894736842114,
    "p": []
   },
   {
    "t": 77052.6315789474,
    "d": 3,
    "l": 157.894736842087,
    "p": []
   },
   {
    "t": 77368.4210526316,
    "d": 0,
    "l": 157.894736842114,
    "p": []
   },
   {
    "t": 77684.2105263158,
    "d": 1,
    "l": 157.894736842105,
    "p": []
   },
   {
    "t": 78000,
    "d": 2,
    "l": 157.894736842105,
    "p": []
   },
   {
    "t": 78315.7894736842,
    "d": 7,
    "l": 157.894736842105,
    "p": []
   },
   {
    "t": 78631.5789473684,
    "d": 4,
    "l": 157.894736842105,
    "p": []
   },
   {
    "t": 78947.3684210526,
    "d": 5,
    "l": 157.894736842105,
    "p": []
   },
   {
    "t": 79263.1578947368,
    "d": 6,
    "l": 157.894736842105,
    "p": []
   },
   {
    "t": 79578.9473684211,
    "d": 7,
    "l": 157.894736842105,
    "p": []
   },
   {
    "t": 79578.9473684211,
    "d": 3,
    "l": 157.894736842105,
    "p": []
   },
   {
    "t": 79894.7368421053,
    "d": 4,
    "l": 157.894736842105,
    "p": []
   },
   {
    "t": 79894.7368421053,
    "d": 0,
    "l": 157.894736842105,
    "p": []
   },
   {
    "t": 80210.5263157895,
    "d": 5,
    "l": 157.894736842105,
    "p": []
   },
   {
    "t": 80210.5263157895,
    "d": 1,
    "l": 157.894736842105,
    "p": []
   },
   {
    "t": 80526.3157894737,
    "d": 6,
    "l": 157.894736842105,
    "p": []
   },
   {
    "t": 80526.3157894737,
    "d": 2,
    "l": 157.894736842105,
    "p": []
   },
   {
    "t": 80842.1052631579,
    "d": 5,
    "l": 315.789473684211,
    "p": []
   },
   {
    "t": 81315.7894736842,
    "d": 7,
    "l": 315.789473684211,
    "p": []
   },
   {
    "t": 81789.4736842105,
    "d": 4,
    "l": 315.789473684211,
    "p": []
   },
   {
    "t": 82263.1578947368,
    "d": 6,
    "l": 315.789473684211,
    "p": []
   },
   {
    "t": 82736.8421052632,
    "d": 5,
    "l": 0,
    "p": []
   },
   {
    "t": 82894.7368421053,
    "d": 7,
    "l": 315.789473684211,
    "p": []
   },
   {
    "t": 83368.4210526316,
    "d": 4,
    "l": 315.789473684211,
    "p": []
   },
   {
    "t": 83842.1052631579,
    "d": 5,
    "l": 315.789473684211,
    "p": []
   },
   {
    "t": 84315.7894736842,
    "d": 7,
    "l": 315.789473684211,
    "p": []
   },
   {
    "t": 84789.4736842105,
    "d": 6,
    "l": 315.789473684211,
    "p": []
   },
   {
    "t": 85263.1578947368,
    "d": 4,
    "l": 0,
    "p": []
   },
   {
    "t": 85421.0526315789,
    "d": 5,
    "l": 315.789473684211,
    "p": []
   },
   {
    "t": 85894.7368421053,
    "d": 7,
    "l": 315.789473684211,
    "p": []
   },
   {
    "t": 86368.4210526316,
    "d": 4,
    "l": 315.789473684211,
    "p": []
   },
   {
    "t": 86842.1052631579,
    "d": 6,
    "l": 315.789473684211,
    "p": []
   },
   {
    "t": 87315.7894736842,
    "d": 5,
    "l": 315.789473684211,
    "p": []
   },
   {
    "t": 87789.4736842105,
    "d": 7,
    "l": 0,
    "p": []
   },
   {
    "t": 87947.3684210526,
    "d": 4,
    "l": 315.789473684211,
    "p": []
   },
   {
    "t": 88421.0526315789,
    "d": 5,
    "l": 315.789473684211,
    "p": []
   },
   {
    "t": 88894.7368421053,
    "d": 7,
    "l": 315.789473684211,
    "p": []
   },
   {
    "t": 89368.4210526316,
    "d": 4,
    "l": 315.789473684211,
    "p": []
   },
   {
    "t": 89842.1052631579,
    "d": 7,
    "l": 315.789473684211,
    "p": []
   },
   {
    "t": 90315.7894736842,
    "d": 6,
    "l": 0,
    "p": []
   },
   {
    "t": 90473.6842105263,
    "d": 5,
    "l": 315.789473684211,
    "p": []
   },
   {
    "t": 90947.3684210526,
    "d": 1,
    "l": 315.789473684211,
    "p": []
   },
   {
    "t": 91421.0526315789,
    "d": 3,
    "l": 315.789473684211,
    "p": []
   },
   {
    "t": 91894.7368421053,
    "d": 0,
    "l": 315.789473684211,
    "p": []
   },
   {
    "t": 92368.4210526316,
    "d": 2,
    "l": 315.789473684211,
    "p": []
   },
   {
    "t": 92842.1052631579,
    "d": 1,
    "l": 0,
    "p": []
   },
   {
    "t": 93000,
    "d": 3,
    "l": 315.789473684211,
    "p": []
   },
   {
    "t": 93473.6842105263,
    "d": 0,
    "l": 315.789473684211,
    "p": []
   },
   {
    "t": 93947.3684210526,
    "d": 1,
    "l": 315.789473684211,
    "p": []
   },
   {
    "t": 94421.0526315789,
    "d": 3,
    "l": 315.789473684211,
    "p": []
   },
   {
    "t": 94894.7368421053,
    "d": 2,
    "l": 315.789473684211,
    "p": []
   },
   {
    "t": 95368.4210526316,
    "d": 0,
    "l": 0,
    "p": []
   },
   {
    "t": 95526.3157894737,
    "d": 1,
    "l": 315.789473684211,
    "p": []
   },
   {
    "t": 96000,
    "d": 3,
    "l": 315.789473684211,
    "p": []
   },
   {
    "t": 96473.6842105263,
    "d": 0,
    "l": 315.789473684211,
    "p": []
   },
   {
    "t": 96947.3684210526,
    "d": 2,
    "l": 315.789473684211,
    "p": []
   },
   {
    "t": 97421.0526315789,
    "d": 1,
    "l": 315.789473684211,
    "p": []
   },
   {
    "t": 97894.7368421053,
    "d": 3,
    "l": 0,
    "p": []
   },
   {
    "t": 98052.6315789474,
    "d": 0,
    "l": 315.789473684211,
    "p": []
   },
   {
    "t": 98526.3157894737,
    "d": 1,
    "l": 315.789473684211,
    "p": []
   },
   {
    "t": 99000,
    "d": 3,
    "l": 315.789473684211,
    "p": []
   },
   {
    "t": 99473.6842105263,
    "d": 0,
    "l": 315.789473684211,
    "p": []
   },
   {
    "t": 99947.3684210526,
    "d": 3,
    "l": 315.789473684211,
    "p": []
   },
   {
    "t": 100421.052631579,
    "d": 0,
    "l": 0,
    "p": []
   },
   {
    "t": 100421.052631579,
    "d": 2,
    "l": 0,
    "p": []
   },
   {
    "t": 100578.947368421,
    "d": 1,
    "l": 315.789473684211,
    "p": []
   },
   {
    "t": 101052.263157895,
    "d": 7,
    "l": 157.894736842105,
    "p": []
   },
   {
    "t": 101368.052631579,
    "d": 4,
    "l": 157.894736842105,
    "p": []
   },
   {
    "t": 101683.842105263,
    "d": 5,
    "l": 157.894736842105,
    "p": []
   },
   {
    "t": 101999.631578947,
    "d": 6,
    "l": 157.894736842105,
    "p": []
   },
   {
    "t": 102315.421052632,
    "d": 7,
    "l": 157.894736842105,
    "p": []
   },
   {
    "t": 102631.210526316,
    "d": 4,
    "l": 157.894736842105,
    "p": []
   },
   {
    "t": 102947,
    "d": 5,
    "l": 473.684210526316,
    "p": []
   },
   {
    "t": 103578.578947368,
    "d": 7,
    "l": 157.894736842105,
    "p": []
   },
   {
    "t": 103894.368421053,
    "d": 4,
    "l": 157.894736842105,
    "p": []
   },
   {
    "t": 104210.157894737,
    "d": 7,
    "l": 157.894736842105,
    "p": []
   },
   {
    "t": 104525.947368421,
    "d": 5,
    "l": 157.894736842105,
    "p": []
   },
   {
    "t": 104841.736842105,
    "d": 6,
    "l": 473.684210526316,
    "p": []
   },
   {
    "t": 105473.315789474,
    "d": 5,
    "l": 473.684210526316,
    "p": []
   },
   {
    "t": 106104.894736842,
    "d": 6,
    "l": 157.894736842105,
    "p": []
   },
   {
    "t": 106420.684210526,
    "d": 7,
    "l": 157.894736842105,
    "p": []
   },
   {
    "t": 106736.473684211,
    "d": 4,
    "l": 473.684210526316,
    "p": []
   },
   {
    "t": 107368.052631579,
    "d": 6,
    "l": 157.894736842105,
    "p": []
   },
   {
    "t": 107683.842105263,
    "d": 7,
    "l": 157.894736842105,
    "p": []
   },
   {
    "t": 107999.631578947,
    "d": 5,
    "l": 473.684210526316,
    "p": []
   },
   {
    "t": 108631.210526316,
    "d": 7,
    "l": 473.684210526316,
    "p": []
   },
   {
    "t": 109262.789473684,
    "d": 4,
    "l": 473.684210526316,
    "p": []
   },
   {
    "t": 109894.368421053,
    "d": 6,
    "l": 473.684210526316,
    "p": []
   },
   {
    "t": 110525.947368421,
    "d": 5,
    "l": 473.684210526316,
    "p": []
   },
   {
    "t": 111157.894736842,
    "d": 3,
    "l": 157.894736842105,
    "p": []
   },
   {
    "t": 111473.684210526,
    "d": 0,
    "l": 0,
    "p": []
   },
   {
    "t": 111789.473684211,
    "d": 1,
    "l": 0,
    "p": []
   },
   {
    "t": 112105.263157895,
    "d": 2,
    "l": 0,
    "p": []
   },
   {
    "t": 112421.052631579,
    "d": 3,
    "l": 0,
    "p": []
   },
   {
    "t": 112736.842105263,
    "d": 0,
    "l": 0,
    "p": []
   },
   {
    "t": 113052.631578947,
    "d": 1,
    "l": 0,
    "p": []
   },
   {
    "t": 113052.631578947,
    "d": 2,
    "l": 0,
    "p": []
   },
   {
    "t": 113684.210526316,
    "d": 3,
    "l": 0,
    "p": []
   },
   {
    "t": 114000,
    "d": 0,
    "l": 0,
    "p": []
   },
   {
    "t": 114315.789473684,
    "d": 3,
    "l": 0,
    "p": []
   },
   {
    "t": 114631.578947368,
    "d": 1,
    "l": 0,
    "p": []
   },
   {
    "t": 114947.368421053,
    "d": 2,
    "l": 473.684210526316,
    "p": []
   },
   {
    "t": 115578.947368421,
    "d": 1,
    "l": 473.684210526316,
    "p": []
   },
   {
    "t": 116210.526315789,
    "d": 2,
    "l": 0,
    "p": []
   },
   {
    "t": 116526.315789474,
    "d": 3,
    "l": 0,
    "p": []
   },
   {
    "t": 116842.105263158,
    "d": 0,
    "l": 473.684210526316,
    "p": []
   },
   {
    "t": 117473.684210526,
    "d": 2,
    "l": 0,
    "p": []
   },
   {
    "t": 117789.473684211,
    "d": 3,
    "l": 0,
    "p": []
   },
   {
    "t": 118105.263157895,
    "d": 1,
    "l": 473.684210526316,
    "p": []
   },
   {
    "t": 118736.842105263,
    "d": 3,
    "l": 473.684210526316,
    "p": []
   },
   {
    "t": 119368.421052632,
    "d": 0,
    "l": 473.684210526316,
    "p": []
   },
   {
    "t": 120000,
    "d": 2,
    "l": 473.684210526316,
    "p": []
   },
   {
    "t": 120631.578947368,
    "d": 1,
    "l": 473.684210526316,
    "p": []
   },
   {
    "t": 121263.157894737,
    "d": 7,
    "l": 157.894736842105,
    "p": []
   },
   {
    "t": 121578.947368421,
    "d": 5,
    "l": 157.894736842105,
    "p": []
   },
   {
    "t": 121894.736842105,
    "d": 7,
    "l": 0,
    "p": []
   },
   {
    "t": 122052.631578947,
    "d": 5,
    "l": 157.894736842105,
    "p": []
   },
   {
    "t": 122368.421052632,
    "d": 7,
    "l": 0,
    "p": []
   },
   {
    "t": 122526.315789474,
    "d": 5,
    "l": 157.894736842105,
    "p": []
   },
   {
    "t": 122842.105263158,
    "d": 4,
    "l": 157.894736842105,
    "p": []
   },
   {
    "t": 123157.894736842,
    "d": 6,
    "l": 157.894736842105,
    "p": []
   },
   {
    "t": 123473.684210526,
    "d": 5,
    "l": 157.894736842105,
    "p": []
   },
   {
    "t": 123789.473684211,
    "d": 6,
    "l": 157.894736842105,
    "p": []
   },
   {
    "t": 124105.263157895,
    "d": 7,
    "l": 157.894736842105,
    "p": []
   },
   {
    "t": 124421.052631579,
    "d": 4,
    "l": 157.894736842105,
    "p": []
   },
   {
    "t": 124736.842105263,
    "d": 5,
    "l": 157.894736842105,
    "p": []
   },
   {
    "t": 125052.631578947,
    "d": 7,
    "l": 473.684210526316,
    "p": []
   },
   {
    "t": 125684.210526316,
    "d": 4,
    "l": 473.684210526316,
    "p": []
   },
   {
    "t": 126315.789473684,
    "d": 3,
    "l": 157.894736842105,
    "p": []
   },
   {
    "t": 126631.578947368,
    "d": 1,
    "l": 157.894736842105,
    "p": []
   },
   {
    "t": 126947.368421053,
    "d": 3,
    "l": 0,
    "p": []
   },
   {
    "t": 127105.263157895,
    "d": 1,
    "l": 157.894736842105,
    "p": []
   },
   {
    "t": 127421.052631579,
    "d": 3,
    "l": 0,
    "p": []
   },
   {
    "t": 127578.947368421,
    "d": 1,
    "l": 157.894736842105,
    "p": []
   },
   {
    "t": 127894.736842105,
    "d": 0,
    "l": 157.894736842105,
    "p": []
   },
   {
    "t": 128210.526315789,
    "d": 2,
    "l": 157.894736842105,
    "p": []
   },
   {
    "t": 128526.315789474,
    "d": 1,
    "l": 157.894736842105,
    "p": []
   },
   {
    "t": 128842.105263158,
    "d": 2,
    "l": 157.894736842105,
    "p": []
   },
   {
    "t": 129157.894736842,
    "d": 3,
    "l": 157.894736842105,
    "p": []
   },
   {
    "t": 129473.684210526,
    "d": 0,
    "l": 157.894736842105,
    "p": []
   },
   {
    "t": 129789.473684211,
    "d": 1,
    "l": 157.894736842105,
    "p": []
   },
   {
    "t": 130105.263157895,
    "d": 3,
    "l": 473.684210526316,
    "p": []
   },
   {
    "t": 130736.842105263,
    "d": 0,
    "l": 473.684210526316,
    "p": []
   },
   {
    "t": 131368.421052632,
    "d": 7,
    "l": 315.789473684211,
    "p": []
   },
   {
    "t": 131842.105263158,
    "d": 6,
    "l": 0,
    "p": []
   },
   {
    "t": 132000,
    "d": 4,
    "l": 315.789473684211,
    "p": []
   },
   {
    "t": 132473.684210526,
    "d": 5,
    "l": 0,
    "p": []
   },
   {
    "t": 132631.578947368,
    "d": 7,
    "l": 157.894736842105,
    "p": []
   },
   {
    "t": 132947.368421053,
    "d": 4,
    "l": 157.894736842105,
    "p": []
   },
   {
    "t": 133263.157894737,
    "d": 6,
    "l": 157.894736842105,
    "p": []
   },
   {
    "t": 133578.947368421,
    "d": 5,
    "l": 157.894736842105,
    "p": []
   },
   {
    "t": 133894.736842105,
    "d": 7,
    "l": 157.894736842105,
    "p": []
   },
   {
    "t": 134210.526315789,
    "d": 4,
    "l": 157.894736842101,
    "p": []
   },
   {
    "t": 134526.315789474,
    "d": 7,
    "l": 0,
    "p": []
   },
   {
    "t": 134684.210526316,
    "d": 6,
    "l": 157.894736842105,
    "p": []
   },
   {
    "t": 135000,
    "d": 5,
    "l": 315.789473684211,
    "p": []
   },
   {
    "t": 135473.684210526,
    "d": 7,
    "l": 157.894736842105,
    "p": []
   },
   {
    "t": 135789.473684211,
    "d": 4,
    "l": 157.894736842096,
    "p": []
   },
   {
    "t": 136105.263157895,
    "d": 6,
    "l": 157.894736842105,
    "p": []
   },
   {
    "t": 136421.052631579,
    "d": 3,
    "l": 315.789473684211,
    "p": []
   },
   {
    "t": 136894.736842105,
    "d": 2,
    "l": 0,
    "p": []
   },
   {
    "t": 137052.631578947,
    "d": 0,
    "l": 315.789473684211,
    "p": []
   },
   {
    "t": 137526.315789474,
    "d": 1,
    "l": 0,
    "p": []
   },
   {
    "t": 137684.210526316,
    "d": 3,
    "l": 157.894736842105,
    "p": []
   },
   {
    "t": 138000,
    "d": 0,
    "l": 157.894736842096,
    "p": []
   },
   {
    "t": 138315.789473684,
    "d": 2,
    "l": 157.894736842105,
    "p": []
   },
   {
    "t": 138631.578947368,
    "d": 1,
    "l": 157.89473684211,
    "p": []
   },
   {
    "t": 138947.368421053,
    "d": 3,
    "l": 157.89473684211,
    "p": []
   },
   {
    "t": 139263.157894737,
    "d": 0,
    "l": 0,
    "p": []
   },
   {
    "t": 139578.947368421,
    "d": 3,
    "l": 0,
    "p": []
   },
   {
    "t": 139736.842105263,
    "d": 2,
    "l": 0,
    "p": []
   },
   {
    "t": 140052.631578947,
    "d": 1,
    "l": 315.789473684211,
    "p": []
   },
   {
    "t": 140526.315789474,
    "d": 3,
    "l": 0,
    "p": []
   },
   {
    "t": 140842.105263158,
    "d": 0,
    "l": 157.89473684211,
    "p": []
   },
   {
    "t": 141157.894736842,
    "d": 2,
    "l": 157.89473684211,
    "p": []
   }
  ],
  "normal": [
   {
    "t": 10105.2631578947,
    "d": 4,
    "l": 0,
    "p": []
   },
   {
    "t": 10421.0526315789,
    "d": 5,
    "l": 0,
    "p": []
   },
   {
    "t": 10736.8421052632,
    "d": 6,
    "l": 0,
    "p": []
   },
   {
    "t": 11052.6315789474,
    "d": 7,
    "l": 0,
    "p": []
   },
   {
    "t": 11368.4210526316,
    "d": 6,
    "l": 0,
    "p": []
   },
   {
    "t": 11684.2105263158,
    "d": 5,
    "l": 0,
    "p": []
   },
   {
    "t": 12000,
    "d": 4,
    "l": 0,
    "p": []
   },
   {
    "t": 12631.5789473684,
    "d": 4,
    "l": 0,
    "p": []
   },
   {
    "t": 12947.3684210526,
    "d": 5,
    "l": 0,
    "p": []
   },
   {
    "t": 13263.1578947368,
    "d": 6,
    "l": 0,
    "p": []
   },
   {
    "t": 13578.9473684211,
    "d": 7,
    "l": 0,
    "p": []
   },
   {
    "t": 13894.7368421053,
    "d": 6,
    "l": 473.684210526316,
    "p": []
   },
   {
    "t": 14526.3157894737,
    "d": 5,
    "l": 473.684210526316,
    "p": []
   },
   {
    "t": 15157.8947368421,
    "d": 7,
    "l": 0,
    "p": []
   },
   {
    "t": 15473.6842105263,
    "d": 6,
    "l": 0,
    "p": []
   },
   {
    "t": 15789.4736842105,
    "d": 5,
    "l": 0,
    "p": []
   },
   {
    "t": 16421.0526315789,
    "d": 6,
    "l": 0,
    "p": []
   },
   {
    "t": 16736.8421052632,
    "d": 5,
    "l": 0,
    "p": []
   },
   {
    "t": 17052.6315789474,
    "d": 4,
    "l": 0,
    "p": []
   },
   {
    "t": 17684.2105263158,
    "d": 3,
    "l": 473.684210526316,
    "p": []
   },
   {
    "t": 17684.2105263158,
    "d": 7,
    "l": 473.684210526316,
    "p": []
   },
   {
    "t": 18315.7894736842,
    "d": 0,
    "l": 473.684210526316,
    "p": []
   },
   {
    "t": 18315.7894736842,
    "d": 4,
    "l": 473.684210526316,
    "p": []
   },
   {
    "t": 18947.3684210526,
    "d": 2,
    "l": 473.684210526316,
    "p": []
   },
   {
    "t": 18947.3684210526,
    "d": 6,
    "l": 473.684210526316,
    "p": []
   },
   {
    "t": 19578.9473684211,
    "d": 1,
    "l": 473.684210526316,
    "p": []
   },
   {
    "t": 19578.9473684211,
    "d": 5,
    "l": 473.684210526316,
    "p": []
   },
   {
    "t": 20210.5263157895,
    "d": 7,
    "l": 0,
    "p": []
   },
   {
    "t": 20526.3157894737,
    "d": 5,
    "l": 0,
    "p": []
   },
   {
    "t": 20842.1052631579,
    "d": 7,
    "l": 0,
    "p": []
   },
   {
    "t": 21473.6842105263,
    "d": 7,
    "l": 0,
    "p": []
   },
   {
    "t": 21789.4736842105,
    "d": 5,
    "l": 0,
    "p": []
   },
   {
    "t": 22105.2631578947,
    "d": 7,
    "l": 0,
    "p": []
   },
   {
    "t": 22736.8421052632,
    "d": 4,
    "l": 473.684210526316,
    "p": []
   },
   {
    "t": 23368.4210526316,
    "d": 7,
    "l": 473.684210526316,
    "p": []
   },
   {
    "t": 24000,
    "d": 5,
    "l": 473.684210526316,
    "p": []
   },
   {
    "t": 24631.5789473684,
    "d": 6,
    "l": 473.684210526316,
    "p": []
   },
   {
    "t": 25263.1578947368,
    "d": 3,
    "l": 0,
    "p": []
   },
   {
    "t": 25578.9473684211,
    "d": 1,
    "l": 0,
    "p": []
   },
   {
    "t": 25894.7368421053,
    "d": 3,
    "l": 0,
    "p": []
   },
   {
    "t": 26526.3157894737,
    "d": 3,
    "l": 0,
    "p": []
   },
   {
    "t": 26842.1052631579,
    "d": 1,
    "l": 0,
    "p": []
   },
   {
    "t": 27157.8947368421,
    "d": 3,
    "l": 0,
    "p": []
   },
   {
    "t": 27789.4736842105,
    "d": 0,
    "l": 473.684210526316,
    "p": []
   },
   {
    "t": 28421.0526315789,
    "d": 3,
    "l": 473.684210526316,
    "p": []
   },
   {
    "t": 29052.6315789474,
    "d": 1,
    "l": 473.684210526316,
    "p": []
   },
   {
    "t": 29684.2105263158,
    "d": 2,
    "l": 473.684210526316,
    "p": []
   },
   {
    "t": 30315.7894736842,
    "d": 4,
    "l": 473.684210526316,
    "p": []
   },
   {
    "t": 30947.3684210526,
    "d": 6,
    "l": 473.684210526316,
    "p": []
   },
   {
    "t": 31578.9473684211,
    "d": 7,
    "l": 473.684210526316,
    "p": []
   },
   {
    "t": 32210.5263157895,
    "d": 5,
    "l": 473.684210526316,
    "p": []
   },
   {
    "t": 32842.1052631579,
    "d": 7,
    "l": 0,
    "p": []
   },
   {
    "t": 33157.8947368421,
    "d": 4,
    "l": 0,
    "p": []
   },
   {
    "t": 33473.6842105263,
    "d": 7,
    "l": 0,
    "p": []
   },
   {
    "t": 33631.5789473684,
    "d": 4,
    "l": 0,
    "p": []
   },
   {
    "t": 33947.3684210526,
    "d": 7,
    "l": 0,
    "p": []
   },
   {
    "t": 34421.0526315789,
    "d": 7,
    "l": 0,
    "p": []
   },
   {
    "t": 34736.8421052632,
    "d": 4,
    "l": 0,
    "p": []
   },
   {
    "t": 35052.6315789474,
    "d": 7,
    "l": 0,
    "p": []
   },
   {
    "t": 35368.4210526316,
    "d": 0,
    "l": 473.684210526316,
    "p": []
   },
   {
    "t": 36000,
    "d": 2,
    "l": 473.684210526316,
    "p": []
   },
   {
    "t": 36631.5789473684,
    "d": 3,
    "l": 473.684210526316,
    "p": []
   },
   {
    "t": 37263.1578947368,
    "d": 1,
    "l": 473.684210526316,
    "p": []
   },
   {
    "t": 37894.7368421053,
    "d": 3,
    "l": 0,
    "p": []
   },
   {
    "t": 38210.5263157895,
    "d": 0,
    "l": 0,
    "p": []
   },
   {
    "t": 38526.3157894737,
    "d": 3,
    "l": 0,
    "p": []
   },
   {
    "t": 38684.2105263158,
    "d": 0,
    "l": 0,
    "p": []
   },
   {
    "t": 39000,
    "d": 3,
    "l": 0,
    "p": []
   },
   {
    "t": 39473.6842105263,
    "d": 3,
    "l": 0,
    "p": []
   },
   {
    "t": 39789.4736842105,
    "d": 0,
    "l": 0,
    "p": []
   },
   {
    "t": 40105.2631578947,
    "d": 3,
    "l": 0,
    "p": []
   },
   {
    "t": 40421.0526315789,
    "d": 4,
    "l": 0,
    "p": []
   },
   {
    "t": 40736.8421052632,
    "d": 5,
    "l": 0,
    "p": []
   },
   {
    "t": 41052.6315789474,
    "d": 6,
    "l": 0,
    "p": []
   },
   {
    "t": 41368.4210526316,
    "d": 7,
    "l": 0,
    "p": []
   },
   {
    "t": 41684.2105263158,
    "d": 6,
    "l": 0,
    "p": []
   },
   {
    "t": 42000,
    "d": 5,
    "l": 0,
    "p": []
   },
   {
    "t": 42315.7894736842,
    "d": 6,
    "l": 0,
    "p": []
   },
   {
    "t": 42631.5789473684,
    "d": 5,
    "l": 0,
    "p": []
   },
   {
    "t": 42947.3684210526,
    "d": 7,
    "l": 0,
    "p": []
   },
   {
    "t": 43263.1578947368,
    "d": 6,
    "l": 0,
    "p": []
   },
   {
    "t": 43578.9473684211,
    "d": 5,
    "l": 0,
    "p": []
   },
   {
    "t": 43894.7368421053,
    "d": 4,
    "l": 0,
    "p": []
   },
   {
    "t": 44210.5263157895,
    "d": 5,
    "l": 0,
    "p": []
   },
   {
    "t": 44526.3157894737,
    "d": 6,
    "l": 0,
    "p": []
   },
   {
    "t": 44842.1052631579,
    "d": 7,
    "l": 0,
    "p": []
   },
   {
    "t": 45157.8947368421,
    "d": 6,
    "l": 0,
    "p": []
   },
   {
    "t": 45473.6842105263,
    "d": 0,
    "l": 0,
    "p": []
   },
   {
    "t": 45789.4736842105,
    "d": 1,
    "l": 0,
    "p": []
   },
   {
    "t": 46105.2631578947,
    "d": 2,
    "l": 0,
    "p": []
   },
   {
    "t": 46421.0526315789,
    "d": 3,
    "l": 0,
    "p": []
   },
   {
    "t": 46736.8421052632,
    "d": 2,
    "l": 0,
    "p": []
   },
   {
    "t": 47052.6315789474,
    "d": 1,
    "l": 0,
    "p": []
   },
   {
    "t": 47368.4210526316,
    "d": 2,
    "l": 0,
    "p": []
   },
   {
    "t": 47684.2105263158,
    "d": 1,
    "l": 0,
    "p": []
   },
   {
    "t": 48000,
    "d": 3,
    "l": 0,
    "p": []
   },
   {
    "t": 48315.7894736842,
    "d": 2,
    "l": 0,
    "p": []
   },
   {
    "t": 48631.5789473684,
    "d": 1,
    "l": 0,
    "p": []
   },
   {
    "t": 48947.3684210526,
    "d": 0,
    "l": 0,
    "p": []
   },
   {
    "t": 49263.1578947368,
    "d": 1,
    "l": 0,
    "p": []
   },
   {
    "t": 49578.9473684211,
    "d": 2,
    "l": 0,
    "p": []
   },
   {
    "t": 49894.7368421053,
    "d": 3,
    "l": 0,
    "p": []
   },
   {
    "t": 50210.5263157895,
    "d": 2,
    "l": 0,
    "p": []
   },
   {
    "t": 50526.3157894737,
    "d": 4,
    "l": 0,
    "p": []
   },
   {
    "t": 50842.1052631579,
    "d": 7,
    "l": 0,
    "p": []
   },
   {
    "t": 51157.8947368421,
    "d": 4,
    "l": 0,
    "p": []
   },
   {
    "t": 51473.6842105263,
    "d": 7,
    "l": 0,
    "p": []
   },
   {
    "t": 51789.4736842105,
    "d": 6,
    "l": 0,
    "p": []
   },
   {
    "t": 52105.2631578947,
    "d": 5,
    "l": 0,
    "p": []
   },
   {
    "t": 52421.0526315789,
    "d": 6,
    "l": 0,
    "p": []
   },
   {
    "t": 53052.6315789474,
    "d": 4,
    "l": 0,
    "p": []
   },
   {
    "t": 53368.4210526316,
    "d": 6,
    "l": 0,
    "p": []
   },
   {
    "t": 53684.2105263158,
    "d": 4,
    "l": 0,
    "p": []
   },
   {
    "t": 54000,
    "d": 6,
    "l": 0,
    "p": []
   },
   {
    "t": 54315.7894736842,
    "d": 7,
    "l": 0,
    "p": []
   },
   {
    "t": 54631.5789473684,
    "d": 5,
    "l": 0,
    "p": []
   },
   {
    "t": 54947.3684210526,
    "d": 7,
    "l": 0,
    "p": []
   },
   {
    "t": 55578.947368421,
    "d": 0,
    "l": 0,
    "p": []
   },
   {
    "t": 55894.7368421053,
    "d": 3,
    "l": 0,
    "p": []
   },
   {
    "t": 56210.5263157895,
    "d": 0,
    "l": 0,
    "p": []
   },
   {
    "t": 56526.3157894737,
    "d": 3,
    "l": 0,
    "p": []
   },
   {
    "t": 56842.1052631579,
    "d": 2,
    "l": 0,
    "p": []
   },
   {
    "t": 57157.8947368421,
    "d": 1,
    "l": 0,
    "p": []
   },
   {
    "t": 57473.6842105263,
    "d": 2,
    "l": 0,
    "p": []
   },
   {
    "t": 58105.2631578947,
    "d": 0,
    "l": 0,
    "p": []
   },
   {
    "t": 58421.0526315789,
    "d": 2,
    "l": 0,
    "p": []
   },
   {
    "t": 58736.8421052632,
    "d": 0,
    "l": 0,
    "p": []
   },
   {
    "t": 59052.6315789474,
    "d": 2,
    "l": 0,
    "p": []
   },
   {
    "t": 59368.4210526316,
    "d": 3,
    "l": 0,
    "p": []
   },
   {
    "t": 59684.2105263158,
    "d": 1,
    "l": 0,
    "p": []
   },
   {
    "t": 60000,
    "d": 3,
    "l": 0,
    "p": []
   },
   {
    "t": 60631.5789473684,
    "d": 7,
    "l": 0,
    "p": []
   },
   {
    "t": 60947.3684210526,
    "d": 7,
    "l": 0,
    "p": []
   },
   {
    "t": 61263.1578947368,
    "d": 7,
    "l": 0,
    "p": []
   },
   {
    "t": 61578.9473684211,
    "d": 7,
    "l": 0,
    "p": []
   },
   {
    "t": 61894.7368421053,
    "d": 5,
    "l": 0,
    "p": []
   },
   {
    "t": 62210.5263157895,
    "d": 5,
    "l": 0,
    "p": []
   },
   {
    "t": 62526.3157894737,
    "d": 5,
    "l": 0,
    "p": []
   },
   {
    "t": 62842.1052631579,
    "d": 5,
    "l": 0,
    "p": []
   },
   {
    "t": 63157.8947368421,
    "d": 6,
    "l": 0,
    "p": []
   },
   {
    "t": 63473.6842105263,
    "d": 6,
    "l": 0,
    "p": []
   },
   {
    "t": 63789.4736842105,
    "d": 6,
    "l": 0,
    "p": []
   },
   {
    "t": 64105.2631578947,
    "d": 6,
    "l": 0,
    "p": []
   },
   {
    "t": 64421.0526315789,
    "d": 4,
    "l": 0,
    "p": []
   },
   {
    "t": 64736.8421052632,
    "d": 4,
    "l": 0,
    "p": []
   },
   {
    "t": 65052.6315789474,
    "d": 4,
    "l": 0,
    "p": []
   },
   {
    "t": 65368.4210526316,
    "d": 4,
    "l": 0,
    "p": []
   },
   {
    "t": 65684.2105263158,
    "d": 3,
    "l": 0,
    "p": []
   },
   {
    "t": 66000,
    "d": 3,
    "l": 0,
    "p": []
   },
   {
    "t": 66315.7894736842,
    "d": 3,
    "l": 0,
    "p": []
   },
   {
    "t": 66631.5789473684,
    "d": 3,
    "l": 0,
    "p": []
   },
   {
    "t": 66947.3684210526,
    "d": 1,
    "l": 0,
    "p": []
   },
   {
    "t": 67263.1578947368,
    "d": 1,
    "l": 0,
    "p": []
   },
   {
    "t": 67578.9473684211,
    "d": 1,
    "l": 0,
    "p": []
   },
   {
    "t": 67894.7368421053,
    "d": 1,
    "l": 0,
    "p": []
   },
   {
    "t": 68210.5263157895,
    "d": 2,
    "l": 0,
    "p": []
   },
   {
    "t": 68526.3157894737,
    "d": 2,
    "l": 0,
    "p": []
   },
   {
    "t": 68842.1052631579,
    "d": 2,
    "l": 0,
    "p": []
   },
   {
    "t": 69157.8947368421,
    "d": 2,
    "l": 0,
    "p": []
   },
   {
    "t": 69473.6842105263,
    "d": 0,
    "l": 0,
    "p": []
   },
   {
    "t": 69789.4736842105,
    "d": 0,
    "l": 0,
    "p": []
   },
   {
    "t": 70105.2631578947,
    "d": 0,
    "l": 0,
    "p": []
   },
   {
    "t": 70421.0526315789,
    "d": 0,
    "l": 0,
    "p": []
   },
   {
    "t": 70736.8421052632,
    "d": 6,
    "l": 315.789473684211,
    "p": []
   },
   {
    "t": 71210.5263157895,
    "d": 7,
    "l": 315.789473684211,
    "p": []
   },
   {
    "t": 71684.2105263158,
    "d": 5,
    "l": 157.894736842105,
    "p": []
   },
   {
    "t": 72000,
    "d": 2,
    "l": 315.789473684211,
    "p": []
   },
   {
    "t": 72473.6842105263,
    "d": 3,
    "l": 315.789473684211,
    "p": []
   },
   {
    "t": 72947.3684210526,
    "d": 1,
    "l": 157.894736842105,
    "p": []
   },
   {
    "t": 73263.1578947368,
    "d": 4,
    "l": 315.789473684211,
    "p": []
   },
   {
    "t": 73736.8421052632,
    "d": 7,
    "l": 315.789473684211,
    "p": []
   },
   {
    "t": 74210.5263157895,
    "d": 5,
    "l": 157.894736842105,
    "p": []
   },
   {
    "t": 74526.3157894737,
    "d": 0,
    "l": 315.789473684211,
    "p": []
   },
   {
    "t": 75000,
    "d": 3,
    "l": 315.789473684211,
    "p": []
   },
   {
    "t": 75473.6842105263,
    "d": 1,
    "l": 157.894736842105,
    "p": []
   },
   {
    "t": 75789.4736842105,
    "d": 7,
    "l": 0,
    "p": []
   },
   {
    "t": 76105.2631578947,
    "d": 4,
    "l": 0,
    "p": []
   },
   {
    "t": 76421.0526315789,
    "d": 5,
    "l": 0,
    "p": []
   },
   {
    "t": 76736.8421052631,
    "d": 6,
    "l": 0,
    "p": []
   },
   {
    "t": 77052.6315789474,
    "d": 3,
    "l": 0,
    "p": []
   },
   {
    "t": 77368.4210526316,
    "d": 0,
    "l": 0,
    "p": []
   },
   {
    "t": 77684.2105263158,
    "d": 1,
    "l": 0,
    "p": []
   },
   {
    "t": 78000,
    "d": 2,
    "l": 0,
    "p": []
   },
   {
    "t": 78315.7894736842,
    "d": 7,
    "l": 0,
    "p": []
   },
   {
    "t": 78631.5789473684,
    "d": 4,
    "l": 0,
    "p": []
   },
   {
    "t": 78947.3684210526,
    "d": 5,
    "l": 0,
    "p": []
   },
   {
    "t": 79263.1578947368,
    "d": 6,
    "l": 0,
    "p": []
   },
   {
    "t": 79578.9473684211,
    "d": 7,
    "l": 0,
    "p": []
   },
   {
    "t": 79578.9473684211,
    "d": 3,
    "l": 0,
    "p": []
   },
   {
    "t": 79894.7368421053,
    "d": 4,
    "l": 0,
    "p": []
   },
   {
    "t": 79894.7368421053,
    "d": 0,
    "l": 0,
    "p": []
   },
   {
    "t": 80210.5263157895,
    "d": 5,
    "l": 0,
    "p": []
   },
   {
    "t": 80210.5263157895,
    "d": 1,
    "l": 0,
    "p": []
   },
   {
    "t": 80526.3157894737,
    "d": 6,
    "l": 0,
    "p": []
   },
   {
    "t": 80526.3157894737,
    "d": 2,
    "l": 0,
    "p": []
   },
   {
    "t": 80842.1052631579,
    "d": 5,
    "l": 315.789473684211,
    "p": []
   },
   {
    "t": 81315.7894736842,
    "d": 7,
    "l": 315.789473684211,
    "p": []
   },
   {
    "t": 81789.4736842105,
    "d": 4,
    "l": 315.789473684211,
    "p": []
   },
   {
    "t": 82263.1578947368,
    "d": 6,
    "l": 315.789473684211,
    "p": []
   },
   {
    "t": 82736.8421052632,
    "d": 5,
    "l": 0,
    "p": []
   },
   {
    "t": 82894.7368421053,
    "d": 7,
    "l": 315.789473684211,
    "p": []
   },
   {
    "t": 83368.4210526316,
    "d": 4,
    "l": 315.789473684211,
    "p": []
   },
   {
    "t": 83842.1052631579,
    "d": 5,
    "l": 315.789473684211,
    "p": []
   },
   {
    "t": 84315.7894736842,
    "d": 7,
    "l": 315.789473684211,
    "p": []
   },
   {
    "t": 84789.4736842105,
    "d": 6,
    "l": 315.789473684211,
    "p": []
   },
   {
    "t": 85263.1578947368,
    "d": 4,
    "l": 0,
    "p": []
   },
   {
    "t": 85421.0526315789,
    "d": 5,
    "l": 315.789473684211,
    "p": []
   },
   {
    "t": 85894.7368421053,
    "d": 7,
    "l": 315.789473684211,
    "p": []
   },
   {
    "t": 86368.4210526316,
    "d": 4,
    "l": 315.789473684211,
    "p": []
   },
   {
    "t": 86842.1052631579,
    "d": 6,
    "l": 315.789473684211,
    "p": []
   },
   {
    "t": 87315.7894736842,
    "d": 5,
    "l": 315.789473684211,
    "p": []
   },
   {
    "t": 87789.4736842105,
    "d": 7,
    "l": 0,
    "p": []
   },
   {
    "t": 87947.3684210526,
    "d": 4,
    "l": 315.789473684211,
    "p": []
   },
   {
    "t": 88421.0526315789,
    "d": 5,
    "l": 315.789473684211,
    "p": []
   },
   {
    "t": 88894.7368421053,
    "d": 7,
    "l": 315.789473684211,
    "p": []
   },
   {
    "t": 89368.4210526316,
    "d": 4,
    "l": 315.789473684211,
    "p": []
   },
   {
    "t": 89842.1052631579,
    "d": 7,
    "l": 315.789473684211,
    "p": []
   },
   {
    "t": 90315.7894736842,
    "d": 6,
    "l": 0,
    "p": []
   },
   {
    "t": 90473.6842105263,
    "d": 5,
    "l": 315.789473684211,
    "p": []
   },
   {
    "t": 90947.3684210526,
    "d": 1,
    "l": 315.789473684211,
    "p": []
   },
   {
    "t": 91421.0526315789,
    "d": 3,
    "l": 315.789473684211,
    "p": []
   },
   {
    "t": 91894.7368421053,
    "d": 0,
    "l": 315.789473684211,
    "p": []
   },
   {
    "t": 92368.4210526316,
    "d": 2,
    "l": 315.789473684211,
    "p": []
   },
   {
    "t": 92842.1052631579,
    "d": 1,
    "l": 0,
    "p": []
   },
   {
    "t": 93000,
    "d": 3,
    "l": 315.789473684211,
    "p": []
   },
   {
    "t": 93473.6842105263,
    "d": 0,
    "l": 315.789473684211,
    "p": []
   },
   {
    "t": 93947.3684210526,
    "d": 1,
    "l": 315.789473684211,
    "p": []
   },
   {
    "t": 94421.0526315789,
    "d": 3,
    "l": 315.789473684211,
    "p": []
   },
   {
    "t": 94894.7368421053,
    "d": 2,
    "l": 315.789473684211,
    "p": []
   },
   {
    "t": 95368.4210526316,
    "d": 0,
    "l": 0,
    "p": []
   },
   {
    "t": 95526.3157894737,
    "d": 1,
    "l": 315.789473684211,
    "p": []
   },
   {
    "t": 96000,
    "d": 3,
    "l": 315.789473684211,
    "p": []
   },
   {
    "t": 96473.6842105263,
    "d": 0,
    "l": 315.789473684211,
    "p": []
   },
   {
    "t": 96947.3684210526,
    "d": 2,
    "l": 315.789473684211,
    "p": []
   },
   {
    "t": 97421.0526315789,
    "d": 1,
    "l": 315.789473684211,
    "p": []
   },
   {
    "t": 97894.7368421053,
    "d": 3,
    "l": 0,
    "p": []
   },
   {
    "t": 98052.6315789474,
    "d": 0,
    "l": 315.789473684211,
    "p": []
   },
   {
    "t": 98526.3157894737,
    "d": 1,
    "l": 315.789473684211,
    "p": []
   },
   {
    "t": 99000,
    "d": 3,
    "l": 315.789473684211,
    "p": []
   },
   {
    "t": 99473.6842105263,
    "d": 0,
    "l": 315.789473684211,
    "p": []
   },
   {
    "t": 99947.3684210526,
    "d": 3,
    "l": 315.789473684211,
    "p": []
   },
   {
    "t": 100421.052631579,
    "d": 2,
    "l": 0,
    "p": []
   },
   {
    "t": 100578.947368421,
    "d": 1,
    "l": 315.789473684211,
    "p": []
   },
   {
    "t": 101052.631578947,
    "d": 4,
    "l": 0,
    "p": []
   },
   {
    "t": 101368.421052632,
    "d": 5,
    "l": 0,
    "p": []
   },
   {
    "t": 101684.210526316,
    "d": 6,
    "l": 0,
    "p": []
   },
   {
    "t": 102000,
    "d": 7,
    "l": 0,
    "p": []
   },
   {
    "t": 102315.789473684,
    "d": 6,
    "l": 0,
    "p": []
   },
   {
    "t": 102631.578947368,
    "d": 5,
    "l": 0,
    "p": []
   },
   {
    "t": 102947.368421053,
    "d": 4,
    "l": 0,
    "p": []
   },
   {
    "t": 103578.947368421,
    "d": 4,
    "l": 0,
    "p": []
   },
   {
    "t": 103894.736842105,
    "d": 5,
    "l": 0,
    "p": []
   },
   {
    "t": 104210.526315789,
    "d": 6,
    "l": 0,
    "p": []
   },
   {
    "t": 104526.315789474,
    "d": 7,
    "l": 0,
    "p": []
   },
   {
    "t": 104842.105263158,
    "d": 6,
    "l": 473.684210526316,
    "p": []
   },
   {
    "t": 105473.684210526,
    "d": 5,
    "l": 473.684210526316,
    "p": []
   },
   {
    "t": 106105.263157895,
    "d": 7,
    "l": 0,
    "p": []
   },
   {
    "t": 106421.052631579,
    "d": 6,
    "l": 0,
    "p": []
   },
   {
    "t": 106736.842105263,
    "d": 5,
    "l": 0,
    "p": []
   },
   {
    "t": 107368.421052632,
    "d": 6,
    "l": 0,
    "p": []
   },
   {
    "t": 107684.210526316,
    "d": 5,
    "l": 0,
    "p": []
   },
   {
    "t": 108000,
    "d": 4,
    "l": 0,
    "p": []
   },
   {
    "t": 108631.578947368,
    "d": 7,
    "l": 473.684210526316,
    "p": []
   },
   {
    "t": 109263.157894737,
    "d": 4,
    "l": 473.684210526316,
    "p": []
   },
   {
    "t": 109894.736842105,
    "d": 6,
    "l": 473.684210526316,
    "p": []
   },
   {
    "t": 110526.315789474,
    "d": 5,
    "l": 473.684210526316,
    "p": []
   },
   {
    "t": 111157.894736842,
    "d": 0,
    "l": 0,
    "p": []
   },
   {
    "t": 111473.684210526,
    "d": 1,
    "l": 0,
    "p": []
   },
   {
    "t": 111789.473684211,
    "d": 2,
    "l": 0,
    "p": []
   },
   {
    "t": 112105.263157895,
    "d": 3,
    "l": 0,
    "p": []
   },
   {
    "t": 112421.052631579,
    "d": 2,
    "l": 0,
    "p": []
   },
   {
    "t": 112736.842105263,
    "d": 1,
    "l": 0,
    "p": []
   },
   {
    "t": 113052.631578947,
    "d": 0,
    "l": 0,
    "p": []
   },
   {
    "t": 113684.210526316,
    "d": 0,
    "l": 0,
    "p": []
   },
   {
    "t": 114000,
    "d": 1,
    "l": 0,
    "p": []
   },
   {
    "t": 114315.789473684,
    "d": 2,
    "l": 0,
    "p": []
   },
   {
    "t": 114631.578947368,
    "d": 3,
    "l": 0,
    "p": []
   },
   {
    "t": 114947.368421053,
    "d": 2,
    "l": 473.684210526316,
    "p": []
   },
   {
    "t": 115578.947368421,
    "d": 1,
    "l": 473.684210526316,
    "p": []
   },
   {
    "t": 116210.526315789,
    "d": 3,
    "l": 0,
    "p": []
   },
   {
    "t": 116526.315789474,
    "d": 2,
    "l": 0,
    "p": []
   },
   {
    "t": 116842.105263158,
    "d": 1,
    "l": 0,
    "p": []
   },
   {
    "t": 117473.684210526,
    "d": 2,
    "l": 0,
    "p": []
   },
   {
    "t": 117789.473684211,
    "d": 1,
    "l": 0,
    "p": []
   },
   {
    "t": 118105.263157895,
    "d": 0,
    "l": 0,
    "p": []
   },
   {
    "t": 118736.842105263,
    "d": 3,
    "l": 473.684210526316,
    "p": []
   },
   {
    "t": 119368.421052632,
    "d": 0,
    "l": 473.684210526316,
    "p": []
   },
   {
    "t": 120000,
    "d": 2,
    "l": 473.684210526316,
    "p": []
   },
   {
    "t": 120631.578947368,
    "d": 1,
    "l": 473.684210526316,
    "p": []
   },
   {
    "t": 121263.157894737,
    "d": 7,
    "l": 0,
    "p": []
   },
   {
    "t": 121578.947368421,
    "d": 5,
    "l": 0,
    "p": []
   },
   {
    "t": 121894.736842105,
    "d": 7,
    "l": 0,
    "p": []
   },
   {
    "t": 122526.315789474,
    "d": 7,
    "l": 0,
    "p": []
   },
   {
    "t": 122842.105263158,
    "d": 5,
    "l": 0,
    "p": []
   },
   {
    "t": 123157.894736842,
    "d": 7,
    "l": 0,
    "p": []
   },
   {
    "t": 123789.473684211,
    "d": 4,
    "l": 473.684210526316,
    "p": []
   },
   {
    "t": 124421.052631579,
    "d": 7,
    "l": 473.684210526316,
    "p": []
   },
   {
    "t": 125052.631578947,
    "d": 5,
    "l": 473.684210526316,
    "p": []
   },
   {
    "t": 125684.210526316,
    "d": 6,
    "l": 473.684210526316,
    "p": []
   },
   {
    "t": 126315.789473684,
    "d": 3,
    "l": 0,
    "p": []
   },
   {
    "t": 126631.578947368,
    "d": 1,
    "l": 0,
    "p": []
   },
   {
    "t": 126947.368421053,
    "d": 3,
    "l": 0,
    "p": []
   },
   {
    "t": 127578.947368421,
    "d": 3,
    "l": 0,
    "p": []
   },
   {
    "t": 127894.736842105,
    "d": 1,
    "l": 0,
    "p": []
   },
   {
    "t": 128210.526315789,
    "d": 3,
    "l": 0,
    "p": []
   },
   {
    "t": 128842.105263158,
    "d": 0,
    "l": 473.684210526316,
    "p": []
   },
   {
    "t": 129473.684210526,
    "d": 3,
    "l": 473.684210526316,
    "p": []
   },
   {
    "t": 130105.263157895,
    "d": 1,
    "l": 473.684210526316,
    "p": []
   },
   {
    "t": 130736.842105263,
    "d": 2,
    "l": 473.684210526316,
    "p": []
   },
   {
    "t": 131368.421052632,
    "d": 4,
    "l": 473.684210526316,
    "p": []
   },
   {
    "t": 132000,
    "d": 6,
    "l": 473.684210526316,
    "p": []
   },
   {
    "t": 132631.578947368,
    "d": 7,
    "l": 473.684210526316,
    "p": []
   },
   {
    "t": 133263.157894737,
    "d": 5,
    "l": 473.684210526316,
    "p": []
   },
   {
    "t": 133894.736842105,
    "d": 7,
    "l": 0,
    "p": []
   },
   {
    "t": 134210.526315789,
    "d": 4,
    "l": 0,
    "p": []
   },
   {
    "t": 134526.315789474,
    "d": 7,
    "l": 0,
    "p": []
   },
   {
    "t": 134684.210526316,
    "d": 4,
    "l": 0,
    "p": []
   },
   {
    "t": 135000,
    "d": 7,
    "l": 0,
    "p": []
   },
   {
    "t": 135473.684210526,
    "d": 7,
    "l": 0,
    "p": []
   },
   {
    "t": 135789.473684211,
    "d": 4,
    "l": 0,
    "p": []
   },
   {
    "t": 136105.263157895,
    "d": 7,
    "l": 0,
    "p": []
   },
   {
    "t": 136421.052631579,
    "d": 0,
    "l": 473.684210526316,
    "p": []
   },
   {
    "t": 137052.631578947,
    "d": 2,
    "l": 473.684210526316,
    "p": []
   },
   {
    "t": 137684.210526316,
    "d": 3,
    "l": 473.684210526316,
    "p": []
   },
   {
    "t": 138315.789473684,
    "d": 1,
    "l": 473.684210526316,
    "p": []
   },
   {
    "t": 138947.368421053,
    "d": 3,
    "l": 0,
    "p": []
   },
   {
    "t": 139263.157894737,
    "d": 0,
    "l": 0,
    "p": []
   },
   {
    "t": 139578.947368421,
    "d": 3,
    "l": 0,
    "p": []
   },
   {
    "t": 139736.842105263,
    "d": 0,
    "l": 0,
    "p": []
   },
   {
    "t": 140052.631578947,
    "d": 3,
    "l": 0,
    "p": []
   },
   {
    "t": 140526.315789474,
    "d": 3,
    "l": 0,
    "p": []
   },
   {
    "t": 140842.105263158,
    "d": 0,
    "l": 0,
    "p": []
   },
   {
    "t": 141157.894736842,
    "d": 3,
    "l": 0,
    "p": []
   }
  ]
 },
 "generatedBy": "Friday Night Funkin' - v0.8.1"
}